RAM.sv
`timescale 1ns / 1ps

module RAM(
    input logic [15:0] axi_data_in,
    input logic [11:0] axi_adr_in,
    input logic axi_write,
    input logic axi_read,
    output logic [31:0] axi_data_out,
    
    input logic [31:0] SEND_DATA,
    input logic [11:0] SEND_ADDR,

    input logic [11:0] READ_ADDRESS,
    
    output logic [15:0] READ_DATA,
    //
    input write_to_cache,
    //
    
    input logic mode,
    input logic clk
    );
 
 reg [31:0] MEM [0:4095];
 
/*always @(posedge clk) begin
    if(mode) begin
        if(axi_write)begin
           MEM[axi_adr_in] <= axi_data_in;
           READ_DATA <= MEM[READ_ADDRESS]; // need changes
        end
        else if(axi_read) axi_data_out <= MEM[axi_adr_in];
    end
    else begin
        MEM[SEND_ADDR] <= SEND_DATA;
    end
 end   */
    
    always @(posedge clk) begin
    if(mode) begin
        if(axi_write)begin
           MEM[axi_adr_in] <= axi_data_in;
        end
        else if(axi_read) axi_data_out <= MEM[axi_adr_in];
    end
    else if(write_to_cache)
                   READ_DATA <= MEM[READ_ADDRESS]; 
    else begin
        MEM[SEND_ADDR] <= SEND_DATA;
    end
 end   
endmodule

Axi_Bridge_fsm.sv
package Axi_Bridge_fsm;
  typedef enum logic [2:0] {  
    bridge_IDLE = 3'b000,
    bridge_ADDR_WRITE,
    bridge_DATA_WRITE,
    bridge_WRITE_RESPONSE,
    bridge_WAIT,
    bridge_ADDR_READ,
    bridge_DATA_READ
  } bridge_fsm;
endpackage

Axi_Bridge.sv
`include "Axi_Bridge_fsm.sv"
import Axi_Bridge_fsm::*;
module Axi_Bridge #(
  parameter DATA_WIDTH = 32
)
(
  input i_clk, i_rstn,
  input [DATA_WIDTH-1:0] i_ARDATA, i_DATA_FROM_RAM,
  input i_ARVALID, i_AWREADY, i_CALC_END,
  input [11:0] i_SAMPLES_NUMBER,
  output logic o_ARREADY, o_AWVALID, o_DATA_LOADED,
  output logic [DATA_WIDTH-1:0] o_AWDATA, o_SAMPLE_ram,
  output logic [1:0] o_AWBURST, o_ARBURST,
  output logic [11:0] o_SAMPLE_INDEX_ram,
  output logic o_WRITE_ram, o_READ_ram
  //output bridge_fsm current_state
);

bridge_fsm state, next_state;
logic [11:0] index_cnt;
bit cnt_en, cnt_clr;

// FSM
always_ff @(posedge i_clk or negedge i_rstn) begin : p_fsm_sync
  if (~i_rstn) begin
    state <= bridge_IDLE;
    index_cnt <= '0;
  end
  else begin
    state <= next_state;
    if(cnt_clr) begin
      index_cnt <= '0;
    end
    else if(cnt_en) begin
      index_cnt <= index_cnt + 1; //tu chyba bedzie ARBURST
    end
  end
end : p_fsm_sync

always_comb begin : p_fsm_comb
  {o_ARREADY, o_AWVALID, o_WRITE_ram, o_READ_ram, o_DATA_LOADED} = 5'b00000;
  {cnt_clr, cnt_en} = 2'b00;
  {o_AWDATA, o_SAMPLE_ram, o_AWBURST, o_ARBURST, o_SAMPLE_INDEX_ram} = 'x;
  case(state)
    bridge_IDLE : begin
      o_ARREADY = 1'b1;
      if(i_ARVALID) begin
        next_state = bridge_READ;
      end
    end

    bridge_READ : begin //Odczyt próbek z wejscia
      o_ARREADY = 1'b1;
      o_WRITE_ram = 1'b1;
      o_SAMPLE_INDEX_ram = index_cnt;
      o_SAMPLE_ram = i_ARDATA;
      //o_ARBURST = ?? TODO
      if(index_cnt == (i_SAMPLES_NUMBER - 1)) begin
        o_DATA_LOADED = 1'b1;
        next_state = bridge_WAIT;
        cnt_clr = 1'b1;
      end
      else if(i_ARVALID) begin
        cnt_en = 1'b1;
      end
    end

    bridge_WAIT : begin
      o_AWVALID = 1'b1;
      if(i_CALC_END && i_AWREADY) begin
        next_state = bridge_WRITE;
      end
    end

    bridge_WRITE : begin
      o_AWVALID = 1'b1;
      o_READ_ram = 1'b1;
      o_SAMPLE_INDEX_ram = index_cnt;
      o_AWDATA = i_DATA_FROM_RAM;
      if (index_cnt == (i_SAMPLES_NUMBER - 1)) begin
        cnt_clr = 1'b1;
        next_state = bridge_IDLE;
      end
      else if (i_AWREADY) begin
        cnt_en = 1'b1;
      end
    end

    default : next_state = bridge_IDLE;
  endcase
end : p_fsm_comb

//assign current_state = state; //current state at the output

endmodule

axi_tb.sv
`include "Axi_Bridge.sv"
`include "RAM.sv"

`timescale 1ns/100ps
module axi_tb #(
    parameter DATA_WIDTH = 32
);
// Inputs
logic i_clk, i_rstn;
logic [15:0] i_ARDATA; 
logic [31:0] i_DATA_FROM_RAM;
logic i_ARVALID, i_AWREADY, i_CALC_END;
logic [11:0] i_SAMPLES_NUMBER;
// Outputs
logic o_ARREADY, o_AWVALID, o_DATA_LOADED;
logic [DATA_WIDTH-1:0] o_AWDATA;
logic [15:0] o_SAMPLE_ram;
logic [1:0] o_AWBURST, o_ARBURST;
logic [11:0] o_SAMPLE_INDEX_ram;
logic o_WRITE_ram, o_READ_ram;
bridge_fsm current_state;

//
logic [31:0] i_RAM_DATA;
logic [11:0] i_RAM_ADDR;
logic LOAD_TO_CACHE;
logic [15:0] o_RAM_DATA;
logic [11:0] ADDR_RAM_TO_CACHE;
logic axi_ncir;
logic [31:0] RAM_interior;
//

//
Axi_Bridge uut(.*);
RAM RAM_uut(
    .axi_data_in(o_SAMPLE_ram),
    .axi_adr_in(o_SAMPLE_INDEX_ram),
    .axi_write(o_WRITE_ram),
    .axi_read(o_READ_ram),
    .axi_data_out(i_DATA_FROM_RAM),
    .SEND_DATA(i_RAM_DATA),
    .SEND_ADDR(i_RAM_ADDR),
    .READ_ADDRESS(ADDR_RAM_TO_CACHE),
    .READ_DATA(o_RAM_DATA),
    .write_to_cache(LOAD_TO_CACHE),
    .mode(axi_ncir),
    .clk(~i_clk)
    );
//
initial begin
    ADDR_RAM_TO_CACHE = 32'd0;
    i_clk = 1'b0; i_rstn = 1'b0;
    i_ARDATA = '0; 
    //i_DATA_FROM_RAM = '0;
    i_CALC_END = 1'b0; i_SAMPLES_NUMBER = '0;
    forever #5 i_clk = ~i_clk;
end

always @(posedge i_clk) begin
    i_ARDATA += 1;
    //i_DATA_FROM_RAM += 2;
end

initial begin

    @(negedge i_clk);
    i_rstn = 1'b1;
    @(posedge i_clk);
    // READ
    i_SAMPLES_NUMBER = 10;
    i_ARVALID = 1'b1;
    @(negedge i_clk);
    axi_ncir = 1'b1;
    repeat(i_SAMPLES_NUMBER) @(posedge i_clk);
    RAM_interior = RAM_uut.MEM[12'd0];
    // WAIT
    i_ARVALID = 1'b0;
    i_AWREADY = 1'b1;
    @(posedge i_clk);
    axi_ncir = 1'b0;
    LOAD_TO_CACHE = 1'b1;
        repeat(i_SAMPLES_NUMBER - 1)begin 
            @(posedge i_clk);
            RAM_interior = RAM_uut.MEM[ADDR_RAM_TO_CACHE];
            ADDR_RAM_TO_CACHE = ADDR_RAM_TO_CACHE + 1;
    end
    i_CALC_END = 1'b0;
    repeat(i_SAMPLES_NUMBER) @(posedge i_clk);
    @(posedge i_clk);
    @(posedge i_clk);
    $finish;
end

initial begin
    $dumpfile("bridge.vcd");
    $dumpvars;
    $dumpon;
end


endmodule

bridge.vcd
$date
	Tue Dec 17 18:27:27 2024
$end
$version
	Icarus Verilog
$end
$timescale
	1ps
$end
$scope module axi_tb $end
$var wire 1 ! o_WRITE_ram $end
$var wire 16 " o_SAMPLE_ram [15:0] $end
$var wire 12 # o_SAMPLE_INDEX_ram [11:0] $end
$var wire 1 $ o_READ_ram $end
$var wire 16 % o_RAM_DATA [15:0] $end
$var wire 1 & o_DATA_LOADED $end
$var wire 1 ' o_AWVALID $end
$var wire 32 ( o_AWDATA [31:0] $end
$var wire 2 ) o_AWBURST [1:0] $end
$var wire 1 * o_ARREADY $end
$var wire 2 + o_ARBURST [1:0] $end
$var wire 32 , i_DATA_FROM_RAM [31:0] $end
$var parameter 32 - DATA_WIDTH $end
$var reg 12 . ADDR_RAM_TO_CACHE [11:0] $end
$var reg 1 / LOAD_TO_CACHE $end
$var reg 32 0 RAM_interior [31:0] $end
$var reg 1 1 axi_ncir $end
$var reg 16 2 i_ARDATA [15:0] $end
$var reg 1 3 i_ARVALID $end
$var reg 1 4 i_AWREADY $end
$var reg 1 5 i_CALC_END $end
$var reg 12 6 i_RAM_ADDR [11:0] $end
$var reg 32 7 i_RAM_DATA [31:0] $end
$var reg 12 8 i_SAMPLES_NUMBER [11:0] $end
$var reg 1 9 i_clk $end
$var reg 1 : i_rstn $end
$scope module RAM_uut $end
$var wire 12 ; READ_ADDRESS [11:0] $end
$var wire 12 < SEND_ADDR [11:0] $end
$var wire 32 = SEND_DATA [31:0] $end
$var wire 1 > clk $end
$var wire 1 1 mode $end
$var wire 1 / write_to_cache $end
$var wire 1 ! axi_write $end
$var wire 1 $ axi_read $end
$var wire 16 ? axi_data_in [15:0] $end
$var wire 12 @ axi_adr_in [11:0] $end
$var reg 16 A READ_DATA [15:0] $end
$var reg 32 B axi_data_out [31:0] $end
$upscope $end
$scope module uut $end
$var wire 16 C i_ARDATA [15:0] $end
$var wire 1 3 i_ARVALID $end
$var wire 1 4 i_AWREADY $end
$var wire 1 5 i_CALC_END $end
$var wire 32 D i_DATA_FROM_RAM [31:0] $end
$var wire 12 E i_SAMPLES_NUMBER [11:0] $end
$var wire 1 9 i_clk $end
$var wire 1 : i_rstn $end
$var parameter 32 F DATA_WIDTH $end
$var reg 12 G index_cnt [11:0] $end
$var reg 2 H next_state [1:0] $end
$var reg 2 I o_ARBURST [1:0] $end
$var reg 1 * o_ARREADY $end
$var reg 2 J o_AWBURST [1:0] $end
$var reg 32 K o_AWDATA [31:0] $end
$var reg 1 ' o_AWVALID $end
$var reg 1 & o_DATA_LOADED $end
$var reg 1 $ o_READ_ram $end
$var reg 12 L o_SAMPLE_INDEX_ram [11:0] $end
$var reg 16 M o_SAMPLE_ram [15:0] $end
$var reg 1 ! o_WRITE_ram $end
$var reg 2 N state [1:0] $end
$var reg 1 O cnt_clr $end
$var reg 1 P cnt_en $end
$scope begin p_fsm_comb $end
$upscope $end
$scope begin p_fsm_sync $end
$upscope $end
$upscope $end
$upscope $end
$enddefinitions $end
$comment Show the parameter values. $end
$dumpall
b100000 F
b100000 -
$end
#0
$dumpvars
0P
0O
b0 N
bx M
bx L
bx K
bx J
bx I
b0 H
b0 G
b0 E
bx D
b0 C
bx B
bx A
bx @
bx ?
1>
bx =
bx <
b0 ;
0:
09
b0 8
bx 7
bx 6
05
x4
x3
b0 2
x1
bx 0
x/
b0 .
bx ,
bx +
1*
bx )
bx (
0'
0&
bx %
0$
bx #
bx "
0!
$end
#5000
1*
b1 2
b1 C
0>
19
#10000
1:
1>
09
#15000
b1 H
1*
b10 2
b10 C
13
b1010 8
b1010 E
0>
19
#20000
11
1>
09
#25000
1P
b11 "
b11 ?
b11 M
b0 #
b0 @
b0 L
1!
b1 N
1*
b11 2
b11 C
0>
19
#30000
1>
09
#35000
b1 G
b100 "
b100 ?
b100 M
b1 #
b1 @
b1 L
1P
1*
1!
b100 2
b100 C
0>
19
#40000
1>
09
#45000
b10 G
b101 "
b101 ?
b101 M
b10 #
b10 @
b10 L
1P
1*
1!
b101 2
b101 C
0>
19
#50000
1>
09
#55000
b11 G
b110 "
b110 ?
b110 M
b11 #
b11 @
b11 L
1P
1*
1!
b110 2
b110 C
0>
19
#60000
1>
09
#65000
b100 G
b111 "
b111 ?
b111 M
b100 #
b100 @
b100 L
1P
1*
1!
b111 2
b111 C
0>
19
#70000
1>
09
#75000
b101 G
b1000 "
b1000 ?
b1000 M
b101 #
b101 @
b101 L
1P
1*
1!
b1000 2
b1000 C
0>
19
#80000
1>
09
#85000
b110 G
b1001 "
b1001 ?
b1001 M
b110 #
b110 @
b110 L
1P
1*
1!
b1001 2
b1001 C
0>
19
#90000
1>
09
#95000
b111 G
b1010 "
b1010 ?
b1010 M
b111 #
b111 @
b111 L
1P
1*
1!
b1010 2
b1010 C
0>
19
#100000
1>
09
#105000
b1000 G
b1011 "
b1011 ?
b1011 M
b1000 #
b1000 @
b1000 L
1P
1*
1!
b1011 2
b1011 C
0>
19
#110000
1>
09
#115000
1O
b11 H
1&
b1001 G
b1100 "
b1100 ?
b1100 M
b1001 #
b1001 @
b1001 L
0P
1*
1!
14
03
b11 0
b1100 2
b1100 C
0>
19
#120000
1>
09
#125000
1'
b0 G
b11 N
bx "
bx ?
bx M
bx #
bx @
bx L
0O
0*
0!
0&
b1101 2
b1101 C
1/
01
0>
19
#130000
b11 %
b11 A
1>
09
#135000
1'
b1 .
b1 ;
b1110 2
b1110 C
0>
19
#140000
b100 %
b100 A
1>
09
#145000
1'
b1111 2
b1111 C
b10 .
b10 ;
b100 0
0>
19
#150000
b101 %
b101 A
1>
09
#155000
1'
b11 .
b11 ;
b101 0
b10000 2
b10000 C
0>
19
#160000
b110 %
b110 A
1>
09
#165000
1'
b10001 2
b10001 C
b100 .
b100 ;
b110 0
0>
19
#170000
b111 %
b111 A
1>
09
#175000
1'
b101 .
b101 ;
b111 0
b10010 2
b10010 C
0>
19
#180000
b1000 %
b1000 A
1>
09
#185000
1'
b10011 2
b10011 C
b110 .
b110 ;
b1000 0
0>
19
#190000
b1001 %
b1001 A
1>
09
#195000
1'
b111 .
b111 ;
b1001 0
b10100 2
b10100 C
0>
19
#200000
b1010 %
b1010 A
1>
09
#205000
1'
b10101 2
b10101 C
b1000 .
b1000 ;
b1010 0
0>
19
#210000
b1011 %
b1011 A
1>
09
#215000
1'
b1001 .
b1001 ;
b1011 0
b10110 2
b10110 C
0>
19
#220000
b1100 %
b1100 A
1>
09
#225000
1'
b10111 2
b10111 C
0>
19
#230000
1>
09
#235000
1'
b11000 2
b11000 C
0>
19
#240000
1>
09
#245000
1'
b11001 2
b11001 C
0>
19
#250000
1>
09
#255000
1'
b11010 2
b11010 C
0>
19
#260000
1>
09
#265000
1'
b11011 2
b11011 C
0>
19
#270000
1>
09
#275000
1'
b11100 2
b11100 C
0>
19
#280000
1>
09
#285000
1'
b11101 2
b11101 C
0>
19
#290000
1>
09
#295000
1'
b11110 2
b11110 C
0>
19
#300000
1>
09
#305000
1'
b11111 2
b11111 C
0>
19
#310000
1>
09
#315000
1'
b100000 2
b100000 C
0>
19
#320000
1>
09
#325000
1'
b100001 2
b100001 C
0>
19
#330000
1>
09
#335000
1'
b100010 2
b100010 C
0>
19
