twidle_fac_gen.sv
// ROM implementation with 4096 twiddle factors in 2's complement
module twiddle_rom #(parameter WIDTH = 32, parameter DEPTH = 4096) (
    input clk, // first change
    input logic [11:0] N,
    input logic [11:0] k_index,
    input logic [11:0] n_index,
    output logic [WIDTH-1:0] data  // Data output
);
    logic [$clog2(DEPTH)-1:0] addr; // Address input
    // Memory array to store twiddle factors
    logic [WIDTH-1:0] rom [0:DEPTH-1];

    // Initialize the ROM with twiddle factors (precomputed values)
    initial begin
        $readmemh("twiddle_factors.hex", rom); // Load from hex file
    end

    // Read data based on address
    always_comb begin
        addr = (4096/N) * k_index * n_index;
        //data = rom[addr];
    end
// second change
    always_ff @(posedge clk)
    data <= rom[addr];

endmodule
/*
// Testbench for twiddle_rom
module tb_twiddle_rom;
    // Parameters
    parameter WIDTH = 32;
    parameter DEPTH = 4096;

    // Signals
    logic [$clog2(DEPTH)-1:0] addr;
    logic [WIDTH-1:0] data;

    // DUT instantiation
    twiddle_rom #(.WIDTH(WIDTH), .DEPTH(DEPTH)) dut (
        .addr(addr),
        .data(data)
    );

    // Testbench variables
    int i;

    // Test procedure
    initial begin
        // Load the twiddle factors into the ROM (requires precomputed hex file)
        $display("Starting twiddle_rom test...");

        // Iterate through all addresses
        for (i = 0; i < DEPTH; i++) begin
            addr = i[$clog2(DEPTH)-1:0]; // Assign address
            #10; // Wait for a few time units

            // Display the result
            $display("Address: %d, Data_re: %b, Data_im = %b", addr, data[31:16], data[15:0]);
        end

        $display("Test completed.");
        $finish;
    end
endmodule
*/

fsm.sv
module fsm
(
    input logic clk,
    input logic ce,
    input logic nrst,
    input logic [11:0] sample_num,
    input logic data_loaded,
    input logic calc_end,
    input logic data_to_cache_loaded,
    output logic load_nCompute,
    output logic count_n_en,
    output logic count_k_en,
    //
    output logic load_to_cache,
    //
    output logic clear,
    output [1:0] state
);

logic [1:0] states;

localparam  IDLE           = 2'b00;
localparam  LOAD_TO_CACHE  = 2'b01;
localparam  CLEAR          = 2'b10;
localparam  COMPUTE        = 2'b11;

always_ff @(posedge clk) begin
if (!nrst) begin
    states <= IDLE;
    load_nCompute <= 1'b1;
    count_n_en <= 1'b0;
    count_k_en <= 1'b0;
    clear <= 1'b0;
    load_to_cache <= 1'b0;
end
else if(ce)begin
    case(states)
        IDLE:
            if(data_loaded) begin
                states <= LOAD_TO_CACHE;
                clear <= 1'b1;
                //
                load_nCompute <= 1'b0;
            end
        LOAD_TO_CACHE:begin
        load_to_cache <= 1'b1;
        count_n_en <= 1'b1;
            if(data_to_cache_loaded) begin
                states <= CLEAR;
                clear <= 1'b0;
                
            end
        end
        CLEAR: begin
            load_to_cache <= 1'b0;
            clear <= 1'b1;
            count_n_en <= 1'b1;
            count_k_en <= 1'b1;
            states <= COMPUTE;
            load_nCompute <= 1'b0;
        end
        COMPUTE: begin
            if(calc_end) begin
                states <= IDLE;
                load_nCompute <= 1'b1;
                count_n_en <= 1'b0;
                count_k_en <= 1'b0;
                end
            end
    endcase
end
end

assign state = states;

endmodule

counter.sv
module counter(
    input clk,
    input ce,
    input nrst,
    input [11:0] max_val,
    output logic [11:0] o_data,
    output logic over
);

logic [11:0] coun_val;

always_ff @(posedge clk)
begin
if (!nrst) begin
    coun_val <= 0;
    over <= 1'b0;
end
else if (ce) begin
    if(coun_val < (max_val-1))begin
    coun_val <= coun_val + 1;
    over <= 1'b0;
    end
    else if(coun_val == max_val - 1) begin
    over <= 1'b1;
    end
    else
    coun_val <= 0;
end
end

always_comb begin
    o_data = coun_val;
end
endmodule

Accumulation_unit.sv
`timescale 1ns / 1ps
//////////////////////////////////////////////////////////////////////////////////
// Company: 
// Engineer: 
// 
// Create Date: 25.11.2024 11:22:18
// Design Name: 
// Module Name: Accumulation_unit
// Project Name: 
// Target Devices: 
// Tool Versions: 
// Description: 
// 
// Dependencies: 
// 
// Revision:
// Revision 0.01 - File Created
// Additional Comments:
// 
//////////////////////////////////////////////////////////////////////////////////


module Accumulation_unit(
    input [31:0] val_a,
    output logic [31:0] val_out,
    input clk,
    input ce,
    input nrst
    );
    
    reg [15:0] accumulated_val_real;
    reg [15:0] accumulated_val_imag;
    
    always_ff @(posedge clk) begin
        if (!nrst) begin
            accumulated_val_real <= 0;
            accumulated_val_imag <= 0;
        end
        else if(ce) begin
        accumulated_val_real <= accumulated_val_real + val_a[31:16];
        accumulated_val_imag <= accumulated_val_imag + val_a[15:0];
        end
    end
    
    always_comb val_out = {accumulated_val_real, accumulated_val_imag};
endmodule

Rounding_unit.sv
`timescale 1ns / 1ps
//////////////////////////////////////////////////////////////////////////////////
// Company: 
// Engineer: 
// 
// Create Date: 25.11.2024 11:19:11
// Design Name: 
// Module Name: Rounding_unit
// Project Name: 
// Target Devices: 
// Tool Versions: 
// Description: 
// 
// Dependencies: 
// 
// Revision:
// Revision 0.01 - File Created
// Additional Comments:
// 
//////////////////////////////////////////////////////////////////////////////////


module Rounding_unit(
    input [31:0] val_in,
    output logic [15:0] val_out
    );
    
    always_comb begin
        val_out <= (val_in >> 16);
    end
endmodule

MUL_UNIT.sv
`timescale 1ns / 1ps


module MUL_UNIT(
    input [15:0] a_val,
    input [15:0] b_val,
    output logic [31:0] result
);

    always_comb begin
        result = a_val * b_val;
    end
endmodule

Cache_memory.sv
`timescale 1ns / 1ps


module Cache_memory(
    input [15:0] data_in,
    input [11:0] write_adr,
    
    input [11:0] read_adr,
    output logic [15:0] read_data,
    
    input clk,
    input write
    );
    
logic [11:0] shifted_write_adr;

d_flip_flop d1(.clk(clk), .d(write_adr), .q(shifted_write_adr));

reg [15:0] MEM [0:4095];

initial MEM[0]=16'd0;

always @(posedge clk) begin
if(write)begin
    MEM[shifted_write_adr] <= data_in;
    end
else
read_data <= MEM[read_adr];
end
endmodule


module d_flip_flop(
    input logic clk,
    input logic [11:0] d,
    output logic [11:0] q
);
always_ff @(posedge clk)
q <= d;
endmodule

RAM.sv
`timescale 1ns / 1ps

module RAM(
    input logic [15:0] axi_data_in,
    input logic [11:0] axi_adr_in,
    input logic axi_write,
    input logic axi_read,
    output logic [31:0] axi_data_out,
    
    input logic [31:0] SEND_DATA,
    input logic [11:0] SEND_ADDR,

    input logic [11:0] READ_ADDRESS,
    
    output logic [15:0] READ_DATA,
    //
    input write_to_cache,
    //
    
    input logic mode,
    input logic clk
    );
 
 reg [31:0] MEM [0:4095];
 
/*always @(posedge clk) begin
    if(mode) begin
        if(axi_write)begin
           MEM[axi_adr_in] <= axi_data_in;
           READ_DATA <= MEM[READ_ADDRESS]; // need changes
        end
        else if(axi_read) axi_data_out <= MEM[axi_adr_in];
    end
    else begin
        MEM[SEND_ADDR] <= SEND_DATA;
    end
 end   */
    
    always @(posedge clk) begin
    if(mode) begin
        if(axi_write)begin
           MEM[axi_adr_in] <= axi_data_in;
        end
        else if(axi_read) axi_data_out <= MEM[axi_adr_in];
    end
    else if(write_to_cache)
        READ_DATA <= MEM[READ_ADDRESS]; 
    else begin
        MEM[SEND_ADDR] <= SEND_DATA;
    end
 end   
endmodule

Axi_Bridge_fsm.sv
package Axi_Bridge_fsm;
  typedef enum logic [2:0] {  
    bridge_IDLE = 3'b000,
    bridge_ADDR_WRITE,
    bridge_DATA_WRITE,
    bridge_WRITE_RESPONSE,
    bridge_WAIT,
    bridge_ADDR_READ,
    bridge_DATA_READ
  } bridge_fsm;
endpackage

Axi_Bridge.sv
`include "Axi_Bridge_fsm.sv"
import Axi_Bridge_fsm::*;
module Axi_Bridge #(
  parameter DATA_WIDTH = 32
)
(
  input i_clk, i_rstn,
  input [DATA_WIDTH-1:0] i_ARDATA, i_DATA_FROM_RAM,
  input i_ARVALID, i_AWREADY, i_CALC_END,
  input [11:0] i_SAMPLES_NUMBER,
  output logic o_ARREADY, o_AWVALID, o_DATA_LOADED,
  output logic [DATA_WIDTH-1:0] o_AWDATA, o_SAMPLE_ram,
  output logic [1:0] o_AWBURST, o_ARBURST,
  output logic [11:0] o_SAMPLE_INDEX_ram,
  output logic o_WRITE_ram, o_READ_ram
  //output bridge_fsm current_state
);

bridge_fsm state, next_state;
logic [11:0] index_cnt;
bit cnt_en, cnt_clr;

// FSM
always_ff @(posedge i_clk or negedge i_rstn) begin : p_fsm_sync
  if (~i_rstn) begin
    state <= bridge_IDLE;
    index_cnt <= '0;
  end
  else begin
    state <= next_state;
    if(cnt_clr) begin
      index_cnt <= '0;
    end
    else if(cnt_en) begin
      index_cnt <= index_cnt + 1; //tu chyba bedzie ARBURST
    end
  end
end : p_fsm_sync

always_comb begin : p_fsm_comb
  {o_ARREADY, o_AWVALID, o_WRITE_ram, o_READ_ram, o_DATA_LOADED} = 5'b00000;
  {cnt_clr, cnt_en} = 2'b00;
  {o_AWDATA, o_SAMPLE_ram, o_AWBURST, o_ARBURST, o_SAMPLE_INDEX_ram} = 'x;
  case(state)
    bridge_IDLE : begin
      o_ARREADY = 1'b1;
      if(i_ARVALID) begin
        next_state = bridge_READ;
      end
    end

    bridge_READ : begin //Odczyt próbek z wejscia
      o_ARREADY = 1'b1;
      o_WRITE_ram = 1'b1;
      o_SAMPLE_INDEX_ram = index_cnt;
      o_SAMPLE_ram = i_ARDATA;
      //o_ARBURST = ?? TODO
      if(index_cnt == (i_SAMPLES_NUMBER - 1)) begin
        o_DATA_LOADED = 1'b1;
        next_state = bridge_WAIT;
        cnt_clr = 1'b1;
      end
      else if(i_ARVALID) begin
        cnt_en = 1'b1;
      end
    end

    bridge_WAIT : begin
      o_AWVALID = 1'b1;
      if(i_CALC_END && i_AWREADY) begin
        next_state = bridge_WRITE;
      end
    end

    bridge_WRITE : begin
      o_AWVALID = 1'b1;
      o_READ_ram = 1'b1;
      o_SAMPLE_INDEX_ram = index_cnt;
      o_AWDATA = i_DATA_FROM_RAM;
      if (index_cnt == (i_SAMPLES_NUMBER - 1)) begin
        cnt_clr = 1'b1;
        next_state = bridge_IDLE;
      end
      else if (i_AWREADY) begin
        cnt_en = 1'b1;
      end
    end

    default : next_state = bridge_IDLE;
  endcase
end : p_fsm_comb

//assign current_state = state; //current state at the output

endmodule

top_fft.sv
`include "RAM.sv"
`include "MUL_UNIT.sv"
`include "Rounding_unit.sv"
`include "Accumulation_unit.sv"
`include "Axi_Bridge.sv"
`include "counter.sv"
`include "fsm.sv"
`include "twidle_fac_gen.sv"
`include "Cache_memory.sv"
/////////////////////////////////////////////////////////
// Missing things:


module top_fft #(parameter N = 2)(
    // AXI BUS
    input               [15:0]  RDATA,
    input                       RVALID,
    output logic                RREADY,
    output logic        [N-1:0] RBURST,
    output logic        [31:0]  WDATA,
    output logic                WVALID,
    input logic                 WREADY,
    output logic        [N-1:0] WBURST,


    input [11:0] SAMP_NUMBER,
    input clk,
    input MAC_nRADIX,
    input n_Reset
);


logic [15:0] CACHE_DATA_IN;
logic [15:0] CACHE_DATA_OUT;
logic [15:0] TW_VAL_REAL;
logic [15:0] TW_VAL_IMAG;
logic [31:0] ACUMULATION_INPUT;
logic [31:0] MUL_REAL_RESULT;
logic [31:0] MUL_IMAG_RESULT;
logic [31:0] SEND_DATA;
logic [11:0] SEND_ADDR;

logic [11:0] N_INDEX;
logic l_nComp;
logic CALC_END;
logic counter_n_en;
logic counter_k_en;
logic counter_n_ovf;
logic device_clear;

logic [15:0] RAM_in_axi;
logic [31:0] DATA_FROM_RAM;
logic [11:0] SAMPLE_INDEX_ram;
logic READ_ram;
logic WRITE_ram;
logic LOADED_DATA;

//
logic ram_to_cache;
logic [1:0] fsm_state;

Axi_Bridge slave(.i_clk(clk), .i_rstn(n_Reset), .i_ARDATA(RDATA),
        .i_DATA_FROM_RAM(DATA_FROM_RAM), .i_ARVALID(RVALID), .i_AWREADY(WREADY),
        .i_CALC_END(CALC_END), .i_SAMPLES_NUMBER(SAMP_NUMBER),
        .o_ARREADY(RREADY), .o_AWVALID(WVALID), .o_DATA_LOADED(LOADED_DATA), 
        .o_AWDATA(WDATA), .o_SAMPLE_ram(RAM_in_axi), .o_AWBURST(WBURST), 
        .o_ARBURST(RBURST), .o_SAMPLE_INDEX_ram(SAMPLE_INDEX_ram),
        .o_WRITE_ram(WRITE_ram), .o_READ_ram(READ_ram)
);

RAM ram1(
        .axi_data_in(RAM_in_axi), 
         .axi_adr_in(SAMPLE_INDEX_ram), 
         .axi_write(WRITE_ram),
         .axi_read(READ_ram),
         .axi_data_out(DATA_FROM_RAM),
         .SEND_DATA(SEND_DATA),
         .SEND_ADDR(SEND_ADDR),
         .READ_ADDRESS(N_INDEX),
         .READ_DATA(CACHE_DATA_IN),
         //
        .write_to_cache(ram_to_cache),
         //
         .mode(l_nComp), // '1' AXI write and read, load to cache, '0' Circiut write
         .clk(clk)
);

Cache_memory c_mem(
        .data_in(CACHE_DATA_IN),
        .write_adr(N_INDEX),
        .read_adr(N_INDEX),
        .read_data(CACHE_DATA_OUT),
        .clk(clk),
        .write(ram_to_cache)
);

MUL_UNIT mul_real(
        .a_val(CACHE_DATA_OUT),
        .b_val(TW_VAL_REAL),
        .result(MUL_REAL_RESULT)
);

MUL_UNIT mul_imag(
        .a_val(CACHE_DATA_OUT),
        .b_val(TW_VAL_IMAG),
        .result(MUL_IMAG_RESULT)
);

Rounding_unit round_real(
        .val_in(MUL_REAL_RESULT),
        .val_out(ACUMULATION_INPUT[31:16])
);

Rounding_unit round_imag(
        .val_in(MUL_IMAG_RESULT),
        .val_out(ACUMULATION_INPUT[15:0])
);

Accumulation_unit acumulation(
        .val_a(ACUMULATION_INPUT),
        .val_out(SEND_DATA),
        .clk(clk),
        .ce(counter_k_en),
        .nrst(device_clear)
);

counter n_counter(
        .clk(clk), 
        .ce(counter_n_en), 
        .nrst(device_clear), 
        .max_val(SAMP_NUMBER), 
        .o_data(N_INDEX), 
        .over(counter_n_ovf)
);

counter k_counter(
        .clk(clk), 
        .ce(counter_k_en & counter_n_ovf), 
        .nrst(device_clear), 
        .max_val(SAMP_NUMBER), 
        .o_data(SEND_ADDR), 
        .over(CALC_END)
);

fsm finit_state(
        .clk(clk),
        .ce(MAC_nRADIX),
        .nrst(n_Reset),
        .sample_num(SAMP_NUMBER),
        .data_loaded(LOADED_DATA),
        .calc_end(CALC_END),
        .load_nCompute(l_nComp),
        .count_n_en(counter_n_en),
        .count_k_en(counter_k_en),
        .clear(device_clear),
        //
        .load_to_cache(ram_to_cache),
        //
        .data_to_cache_loaded(counter_n_ovf),
        .state(fsm_state)

);

twiddle_rom tw_gen(
        .clk(clk),
        .N(SAMP_NUMBER), 
        .k_index(SEND_ADDR), 
        .n_index(N_INDEX), 
        .data({TW_VAL_REAL,TW_VAL_IMAG})
);

endmodule : top_fft

top_fft_tb.sv
`include "top_fft.sv"

module top_fft_tb;
parameter DATA_WIDTH = 32;
// Inputs
logic i_clk, i_rstn;
logic [15:0] i_ARDATA; 
logic [31:0] i_DATA_FROM_RAM;
logic i_ARVALID, i_AWREADY, i_CALC_END;
logic [11:0] i_SAMPLES_NUMBER;
// Outputs
logic o_ARREADY, o_AWVALID, o_DATA_LOADED;
logic [DATA_WIDTH-1:0] o_AWDATA;
logic [15:0] o_SAMPLE_ram;
logic [1:0] o_AWBURST, o_ARBURST;
logic [11:0] o_SAMPLE_INDEX_ram;
logic o_WRITE_ram, o_READ_ram;
bridge_fsm current_state;

//
logic MAC_nRADIX;

top_fft dut(
    .clk(i_clk),
    .n_Reset(i_rstn),
    .MAC_nRADIX(MAC_nRADIX),
    .SAMP_NUMBER(i_SAMPLES_NUMBER),
    .RDATA(i_ARDATA),
    .RVALID(i_ARVALID),
    .RREADY(o_ARREADY),
    .RBURST(o_ARBURST),
    .WDATA(o_AWDATA),
    .WVALID(o_AWVALID),
    .WREADY(i_AWREADY),
    .WBURST(o_AWBURST)
);

initial begin
    MAC_nRADIX = 1'b1;
    i_clk = 1'b0; i_rstn = 1'b0;
    i_ARDATA = '0; 
    //i_DATA_FROM_RAM = '0;
    i_SAMPLES_NUMBER = '0;
    forever #5 i_clk = ~i_clk;
end

always @(posedge i_clk) begin
    i_ARDATA += 1;
    //i_DATA_FROM_RAM += 2;
end

initial begin

    @(negedge i_clk);
    i_rstn = 1'b1;
    @(posedge i_clk);
    // READ
    i_SAMPLES_NUMBER = 10;
    i_ARVALID = 1'b1;
    repeat(i_SAMPLES_NUMBER) @(posedge i_clk);
    // WAIT
    i_ARVALID = 1'b0;
    i_AWREADY = 1'b1;
    @(posedge i_clk);
    @(posedge i_clk);
    #500 $finish;
end

initial begin
    $dumpfile("top.vcd");
    $dumpvars;
    $dumpon;
end

endmodule

top.vcd
$date
	Wed Dec 18 14:57:09 2024
$end
$version
	Icarus Verilog
$end
$timescale
	1ps
$end
$scope module top_fft_tb $end
$var wire 1 ! o_AWVALID $end
$var wire 32 " o_AWDATA [31:0] $end
$var wire 2 # o_AWBURST [1:0] $end
$var wire 1 $ o_ARREADY $end
$var wire 2 % o_ARBURST [1:0] $end
$var reg 1 & MAC_nRADIX $end
$var reg 16 ' i_ARDATA [15:0] $end
$var reg 1 ( i_ARVALID $end
$var reg 1 ) i_AWREADY $end
$var reg 12 * i_SAMPLES_NUMBER [11:0] $end
$var reg 1 + i_clk $end
$var reg 1 , i_rstn $end
$scope module dut $end
$var wire 1 & MAC_nRADIX $end
$var wire 16 - RDATA [15:0] $end
$var wire 1 ( RVALID $end
$var wire 12 . SAMP_NUMBER [11:0] $end
$var wire 1 ) WREADY $end
$var wire 1 + clk $end
$var wire 1 , n_Reset $end
$var wire 1 / ram_to_cache $end
$var wire 1 0 l_nComp $end
$var wire 2 1 fsm_state [1:0] $end
$var wire 1 2 device_clear $end
$var wire 1 3 counter_n_ovf $end
$var wire 1 4 counter_n_en $end
$var wire 1 5 counter_k_en $end
$var wire 1 ! WVALID $end
$var wire 1 6 WRITE_ram $end
$var wire 32 7 WDATA [31:0] $end
$var wire 2 8 WBURST [1:0] $end
$var wire 16 9 TW_VAL_REAL [15:0] $end
$var wire 16 : TW_VAL_IMAG [15:0] $end
$var wire 32 ; SEND_DATA [31:0] $end
$var wire 12 < SEND_ADDR [11:0] $end
$var wire 12 = SAMPLE_INDEX_ram [11:0] $end
$var wire 1 $ RREADY $end
$var wire 1 > READ_ram $end
$var wire 2 ? RBURST [1:0] $end
$var wire 16 @ RAM_in_axi [15:0] $end
$var wire 12 A N_INDEX [11:0] $end
$var wire 32 B MUL_REAL_RESULT [31:0] $end
$var wire 32 C MUL_IMAG_RESULT [31:0] $end
$var wire 1 D LOADED_DATA $end
$var wire 32 E DATA_FROM_RAM [31:0] $end
$var wire 1 F CALC_END $end
$var wire 16 G CACHE_DATA_OUT [15:0] $end
$var wire 16 H CACHE_DATA_IN [15:0] $end
$var wire 32 I ACUMULATION_INPUT [31:0] $end
$scope module acumulation $end
$var wire 1 + clk $end
$var wire 32 J val_a [31:0] $end
$var wire 1 2 nrst $end
$var wire 1 5 ce $end
$var reg 16 K accumulated_val_imag [15:0] $end
$var reg 16 L accumulated_val_real [15:0] $end
$var reg 32 M val_out [31:0] $end
$upscope $end
$scope module c_mem $end
$var wire 1 + clk $end
$var wire 12 N write_adr [11:0] $end
$var wire 1 / write $end
$var wire 12 O shifted_write_adr [11:0] $end
$var wire 12 P read_adr [11:0] $end
$var wire 16 Q data_in [15:0] $end
$var reg 16 R read_data [15:0] $end
$scope module d1 $end
$var wire 1 + clk $end
$var wire 12 S d [11:0] $end
$var reg 12 T q [11:0] $end
$upscope $end
$upscope $end
$scope module finit_state $end
$var wire 1 & ce $end
$var wire 1 + clk $end
$var wire 1 , nrst $end
$var wire 12 U sample_num [11:0] $end
$var wire 2 V state [1:0] $end
$var wire 1 3 data_to_cache_loaded $end
$var wire 1 D data_loaded $end
$var wire 1 F calc_end $end
$var reg 1 2 clear $end
$var reg 1 5 count_k_en $end
$var reg 1 4 count_n_en $end
$var reg 1 0 load_nCompute $end
$var reg 1 / load_to_cache $end
$var reg 2 W states [1:0] $end
$upscope $end
$scope module k_counter $end
$var wire 1 X ce $end
$var wire 1 + clk $end
$var wire 12 Y max_val [11:0] $end
$var wire 1 2 nrst $end
$var reg 12 Z coun_val [11:0] $end
$var reg 12 [ o_data [11:0] $end
$var reg 1 F over $end
$upscope $end
$scope module mul_imag $end
$var wire 16 \ a_val [15:0] $end
$var wire 16 ] b_val [15:0] $end
$var reg 32 ^ result [31:0] $end
$upscope $end
$scope module mul_real $end
$var wire 16 _ a_val [15:0] $end
$var wire 16 ` b_val [15:0] $end
$var reg 32 a result [31:0] $end
$upscope $end
$scope module n_counter $end
$var wire 1 4 ce $end
$var wire 1 + clk $end
$var wire 12 b max_val [11:0] $end
$var wire 1 2 nrst $end
$var reg 12 c coun_val [11:0] $end
$var reg 12 d o_data [11:0] $end
$var reg 1 3 over $end
$upscope $end
$scope module ram1 $end
$var wire 12 e READ_ADDRESS [11:0] $end
$var wire 12 f SEND_ADDR [11:0] $end
$var wire 32 g SEND_DATA [31:0] $end
$var wire 1 + clk $end
$var wire 1 0 mode $end
$var wire 1 / write_to_cache $end
$var wire 1 6 axi_write $end
$var wire 1 > axi_read $end
$var wire 16 h axi_data_in [15:0] $end
$var wire 12 i axi_adr_in [11:0] $end
$var reg 16 j READ_DATA [15:0] $end
$var reg 32 k axi_data_out [31:0] $end
$upscope $end
$scope module round_imag $end
$var wire 32 l val_in [31:0] $end
$var wire 16 m val_out [15:0] $end
$upscope $end
$scope module round_real $end
$var wire 32 n val_in [31:0] $end
$var wire 16 o val_out [15:0] $end
$upscope $end
$scope module slave $end
$var wire 16 p i_ARDATA [15:0] $end
$var wire 1 ( i_ARVALID $end
$var wire 1 ) i_AWREADY $end
$var wire 1 F i_CALC_END $end
$var wire 32 q i_DATA_FROM_RAM [31:0] $end
$var wire 12 r i_SAMPLES_NUMBER [11:0] $end
$var wire 1 + i_clk $end
$var wire 1 , i_rstn $end
$var reg 12 s index_cnt [11:0] $end
$var reg 2 t next_state [1:0] $end
$var reg 2 u o_ARBURST [1:0] $end
$var reg 1 $ o_ARREADY $end
$var reg 2 v o_AWBURST [1:0] $end
$var reg 32 w o_AWDATA [31:0] $end
$var reg 1 ! o_AWVALID $end
$var reg 1 D o_DATA_LOADED $end
$var reg 1 > o_READ_ram $end
$var reg 12 x o_SAMPLE_INDEX_ram [11:0] $end
$var reg 16 y o_SAMPLE_ram [15:0] $end
$var reg 1 6 o_WRITE_ram $end
$var reg 2 z state [1:0] $end
$var reg 1 { cnt_clr $end
$var reg 1 | cnt_en $end
$scope begin p_fsm_comb $end
$upscope $end
$scope begin p_fsm_sync $end
$upscope $end
$upscope $end
$scope module tw_gen $end
$var wire 12 } N [11:0] $end
$var wire 1 + clk $end
$var wire 12 ~ k_index [11:0] $end
$var wire 12 !" n_index [11:0] $end
$var reg 12 "" addr [11:0] $end
$var reg 32 #" data [31:0] $end
$upscope $end
$upscope $end
$upscope $end
$enddefinitions $end
#0
$dumpvars
bx #"
bx ""
bx !"
bx ~
b0 }
0|
0{
b0 z
bx y
bx x
bx w
bx v
bx u
b0 t
b0 s
b0 r
bx q
b0 p
bx o
bx n
bx m
bx l
bx k
bx j
bx i
bx h
bx g
bx f
bx e
bx d
bx c
b0 b
bx a
bx `
bx _
bx ^
bx ]
bx \
bx [
bx Z
b0 Y
xX
bx W
bx V
b0 U
bx T
bx S
bx R
bx Q
bx P
bx O
bx N
bx M
bx L
bx K
bx J
bx I
bx H
bx G
xF
bx E
0D
bx C
bx B
bx A
bx @
bx ?
0>
bx =
bx <
bx ;
bx :
bx 9
bx 8
bx 7
06
x5
x4
x3
x2
bx 1
x0
x/
b0 .
b0 -
0,
0+
b0 *
x)
x(
b0 '
1&
bx %
1$
bx #
bx "
0!
$end
#5000
0X
0/
02
05
04
10
b0 1
b0 V
b0 W
1$
b1 '
b1 -
b1 p
1+
#10000
1,
0+
#15000
b0 ""
b0 <
b0 [
b0 f
b0 ~
b0 A
b0 N
b0 P
b0 S
b0 d
b0 e
b0 !"
b0 ;
b0 M
b0 g
0F
b0 Z
03
b0 c
b0 K
b0 L
b1 t
1$
b10 '
b10 -
b10 p
1(
b11 *
b11 .
b11 U
b11 Y
b11 b
b11 r
b11 }
1+
#20000
0+
#25000
b0 m
b0 I
b0 J
b0 o
b0 C
b0 ^
b0 l
b0 B
b0 a
b0 n
b0 :
b0 ]
b111111111111111 9
b111111111111111 `
1|
b11 @
b11 h
b11 y
b0 =
b0 i
b0 x
16
b0 O
b0 T
b0 G
b0 R
b0 \
b0 _
b1111111111111110000000000000000 #"
b1 z
1$
b11 '
b11 -
b11 p
1+
#30000
0+
#35000
b1 s
b100 @
b100 h
b100 y
b1 =
b1 i
b1 x
1|
1$
16
b100 '
b100 -
b100 p
1+
#40000
0+
#45000
1{
b11 t
1D
b10 s
b101 @
b101 h
b101 y
b10 =
b10 i
b10 x
0|
1$
16
1)
0(
b101 '
b101 -
b101 p
1+
#50000
0+
#55000
1!
00
12
b1 1
b1 V
b1 W
b0 s
b11 z
bx @
bx h
bx y
bx =
bx i
bx x
0{
0$
06
0D
b110 '
b110 -
b110 p
1+
#60000
0+
#65000
14
1/
1!
b111 '
b111 -
b111 p
1+
#70000
0+
#75000
b1 A
b1 N
b1 P
b1 S
b1 d
b1 e
b1 !"
b1 c
b0 H
b0 Q
b0 j
1!
b1000 '
b1000 -
b1000 p
1+
#80000
0+
#85000
b10 A
b10 N
b10 P
b10 S
b10 d
b10 e
b10 !"
b100 H
b100 Q
b100 j
b1 O
b1 T
b10 c
1!
b1001 '
b1001 -
b1001 p
1+
#90000
0+
#95000
13
b10 O
b10 T
b101 H
b101 Q
b101 j
1!
b1010 '
b1010 -
b1010 p
1+
#100000
0+
#105000
02
b10 1
b10 V
b10 W
1!
b1011 '
b1011 -
b1011 p
1+
#110000
0+
#115000
b0 A
b0 N
b0 P
b0 S
b0 d
b0 e
b0 !"
b11 1
b11 V
b11 W
15
12
0/
03
b0 c
1!
b1100 '
b1100 -
b1100 p
1+
#120000
0+
#125000
b1 A
b1 N
b1 P
b1 S
b1 d
b1 e
b1 !"
b0 O
b0 T
b1 c
1!
b1101 '
b1101 -
b1101 p
1+
#130000
0+
#135000
b10000000000000000 I
b10000000000000000 J
b1 o
b10 A
b10 N
b10 P
b10 S
b10 d
b10 e
b10 !"
b11111111111111100 B
b11111111111111100 a
b11111111111111100 n
b10 c
b100 G
b100 R
b100 \
b100 _
b1 O
b1 T
1!
b1110 '
b1110 -
b1110 p
1+
#140000
0+
#145000
b100000000000000000 I
b100000000000000000 J
b10 o
b100111111111111011 B
b100111111111111011 a
b100111111111111011 n
b10000000000000000 ;
b10000000000000000 M
b10000000000000000 g
1X
b10 O
b10 T
b101 G
b101 R
b101 \
b101 _
b1 L
13
1!
b1111 '
b1111 -
b1111 p
1+
#150000
0+
#155000
b101010101010 ""
b1 <
b1 [
b1 f
b1 ~
b110000000000000000 ;
b110000000000000000 M
b110000000000000000 g
b1 Z
b11 L
1!
b10000 '
b10000 -
b10000 p
1+
#160000
0+
#165000
b11 o
b110000000000000010 I
b110000000000000010 J
b10 m
b10101010100 ""
b111011111101101111 B
b111011111101101111 a
b111011111101101111 n
b100010100111101000 C
b100010100111101000 ^
b100010100111101000 l
b1010000000000000000 ;
b1010000000000000000 M
b1010000000000000000 g
b10 <
b10 [
b10 f
b10 ~
b110111011001000 :
b110111011001000 ]
b1011111111100011 9
b1011111111100011 `
b101 L
b10 Z
b10111111111000110110111011001000 #"
1!
b10001 '
b10001 -
b10001 p
1+
#170000
0+
#175000
b101101010100011001 C
b101101010100011001 ^
b101101010100011001 l
b111100000100100111 B
b111100000100100111 a
b111100000100100111 n
b1001000100000101 :
b1001000100000101 ]
b1100000000111011 9
b1100000000111011 `
b10 t
b10000000000000000010 ;
b10000000000000000010 M
b10000000000000000010 g
b11000000001110111001000100000101 #"
1F
b10 K
b1000 L
1!
b10010 '
b10010 -
b10010 p
1+
#180000
0+
#185000
b10110000000000000100 ;
b10110000000000000100 M
b10110000000000000100 g
0X
1|
b0 =
b0 i
b0 x
1>
b100 K
b1011 L
05
04
10
b0 1
b0 V
b0 W
b10 z
1!
b10011 '
b10011 -
b10011 p
1+
#190000
0+
#195000
b10000000000000000 "
b10000000000000000 7
b10000000000000000 w
b10000000000000000 E
b10000000000000000 k
b10000000000000000 q
b1 s
b1 =
b1 i
b1 x
1|
1!
1>
b10100 '
b10100 -
b10100 p
1+
#200000
0+
#205000
b0 t
1{
b110000000000000000 E
b110000000000000000 k
b110000000000000000 q
b10 s
b110000000000000000 "
b110000000000000000 7
b110000000000000000 w
b10 =
b10 i
b10 x
0|
1!
1>
b10101 '
b10101 -
b10101 p
1+
#210000
0+
#215000
1$
b10000000000000000010 E
b10000000000000000010 k
b10000000000000000010 q
b0 s
b0 z
bx "
bx 7
bx w
bx =
bx i
bx x
0{
0!
0>
b10110 '
b10110 -
b10110 p
1+
#220000
0+
#225000
1$
b10111 '
b10111 -
b10111 p
1+
#230000
0+
#235000
1$
b11000 '
b11000 -
b11000 p
1+
#240000
0+
#245000
1$
b11001 '
b11001 -
b11001 p
1+
#250000
0+
#255000
1$
b11010 '
b11010 -
b11010 p
1+
#260000
0+
#265000
1$
b11011 '
b11011 -
b11011 p
1+
#270000
0+
#275000
1$
b11100 '
b11100 -
b11100 p
1+
#280000
0+
#285000
1$
b11101 '
b11101 -
b11101 p
1+
#290000
0+
#295000
1$
b11110 '
b11110 -
b11110 p
1+
#300000
0+
#305000
1$
b11111 '
b11111 -
b11111 p
1+
#310000
0+
#315000
1$
b100000 '
b100000 -
b100000 p
1+
#320000
0+
#325000
1$
b100001 '
b100001 -
b100001 p
1+
#330000
0+
#335000
1$
b100010 '
b100010 -
b100010 p
1+
#340000
0+
#345000
1$
b100011 '
b100011 -
b100011 p
1+
#350000
0+
