twidle_fac_gen.sv
// ROM implementation with 4096 twiddle factors in 2's complement
module twiddle_rom #(parameter WIDTH = 32, parameter DEPTH = 4096) (
    input logic [11:0] N,
    input logic [11:0] k_index,
    input logic [11:0] n_index,
    output logic [WIDTH-1:0] data  // Data output
);
    logic [$clog2(DEPTH)-1:0] addr; // Address input
    // Memory array to store twiddle factors
    logic [WIDTH-1:0] rom [0:DEPTH-1];

    // Initialize the ROM with twiddle factors (precomputed values)
    initial begin
        $readmemh("../FFT/twiddle_factors.hex", rom); // Load from hex file
    end

    // Read data based on address
    always_comb begin
        addr = (4096/N) * k_index * n_index;
        data = rom[addr];
    end

endmodule
/*
// Testbench for twiddle_rom
module tb_twiddle_rom;
    // Parameters
    parameter WIDTH = 32;
    parameter DEPTH = 4096;

    // Signals
    logic [$clog2(DEPTH)-1:0] addr;
    logic [WIDTH-1:0] data;

    // DUT instantiation
    twiddle_rom #(.WIDTH(WIDTH), .DEPTH(DEPTH)) dut (
        .addr(addr),
        .data(data)
    );

    // Testbench variables
    int i;

    // Test procedure
    initial begin
        // Load the twiddle factors into the ROM (requires precomputed hex file)
        $display("Starting twiddle_rom test...");

        // Iterate through all addresses
        for (i = 0; i < DEPTH; i++) begin
            addr = i[$clog2(DEPTH)-1:0]; // Assign address
            #10; // Wait for a few time units

            // Display the result
            $display("Address: %d, Data_re: %b, Data_im = %b", addr, data[31:16], data[15:0]);
        end

        $display("Test completed.");
        $finish;
    end
endmodule
*/

fsm.sv
module fsm
(
    input logic clk,
    input logic ce,
    input logic nrst,
    input logic [11:0] sample_num,
    input logic data_loaded,
    input logic calc_end,
    input logic data_to_cache_loaded,
    output logic load_nCompute,
    output logic count_n_en,
    output logic count_k_en,
    //
    output logic load_to_cache,
    //
    output logic clear,
    output [1:0] state
);

logic [1:0] states;

localparam  IDLE           = 2'b00;
localparam  LOAD_TO_CACHE  = 2'b01;
localparam  CLEAR          = 2'b10;
localparam  COMPUTE        = 2'b11;

always_ff @(posedge clk) begin
if (!nrst) begin
    states <= IDLE;
    load_nCompute <= 1'b1;
    count_n_en <= 1'b0;
    count_k_en <= 1'b0;
    clear <= 1'b0;
    load_to_cache <= 1'b0;
end
else if(ce)begin
    case(states)
        IDLE:
            if(data_loaded) begin
                states <= LOAD_TO_CACHE;
                count_n_en <= 1'b1;
                clear <= 1'b1;
                //
                load_to_cache <= 1'b1;
                load_nCompute <= 1'b0;
            end
        LOAD_TO_CACHE:
            if(data_to_cache_loaded) begin
                states <= CLEAR;
                clear <= 1'b0;
                load_to_cache <= 1'b0;
            end
        CLEAR: begin
            clear <= 1'b1;
            count_n_en <= 1'b1;
            count_k_en <= 1'b1;
            states <= COMPUTE;
            load_nCompute <= 1'b0;
        end
        COMPUTE: begin
            if(calc_end) begin
                states <= IDLE;
                load_nCompute <= 1'b1;
                count_n_en <= 1'b0;
                count_k_en <= 1'b0;
                end
            end
    endcase
end
end

assign state = states;

endmodule

counter.sv
module counter(
    input clk,
    input ce,
    input nrst,
    input [11:0] max_val,
    output logic [11:0] o_data,
    output logic over
);

logic [11:0] coun_val;

always_ff @(posedge clk)
begin
if (!nrst) begin
    coun_val <= 0;
end
else if (ce) begin
    if(coun_val < max_val)
    coun_val <= coun_val + 1;
    else 
    coun_val <= 0;
end
end

always_comb begin
    o_data = coun_val;
    over = ((o_data == max_val) && ce);
end
endmodule

Accumulation_unit.sv
`timescale 1ns / 1ps
//////////////////////////////////////////////////////////////////////////////////
// Company: 
// Engineer: 
// 
// Create Date: 25.11.2024 11:22:18
// Design Name: 
// Module Name: Accumulation_unit
// Project Name: 
// Target Devices: 
// Tool Versions: 
// Description: 
// 
// Dependencies: 
// 
// Revision:
// Revision 0.01 - File Created
// Additional Comments:
// 
//////////////////////////////////////////////////////////////////////////////////


module Accumulation_unit(
    input [31:0] val_a,
    output logic [31:0] val_out,
    input clk,
    input ce,
    input nrst
    );
    
    reg [15:0] accumulated_val_real;
    reg [15:0] accumulated_val_imag;
    
    always_ff @(posedge clk) begin
        if (!nrst) begin
            accumulated_val_real <= 0;
            accumulated_val_imag <= 0;
        end
        else if(ce) begin
        accumulated_val_real <= accumulated_val_real + val_a[31:16];
        accumulated_val_imag <= accumulated_val_imag + val_a[15:0];
        end
    end
    
    always_comb val_out = {accumulated_val_real, accumulated_val_imag};
endmodule

Rounding_unit.sv
`timescale 1ns / 1ps

module Rounding_unit(
    input [31:0] val_in,
    output  [15:0] val_out
    );

        assign val_out = val_in[31:16];

endmodule

MUL_UNIT.sv
`timescale 1ns / 1ps


module MUL_UNIT(
    input [15:0] a_val,
    input [15:0] b_val,
    output logic [31:0] result
);

    always_comb begin
        result = a_val * b_val;
    end
endmodule

Cache_memory.sv
`timescale 1ns / 1ps
//////////////////////////////////////////////////////////////////////////////////
// Company: 
// Engineer: 
// 
// Create Date: 23.11.2024 23:45:49
// Design Name: 
// Module Name: Cache_memory
// Project Name: 
// Target Devices: 
// Tool Versions: 
// Description: 
// 
// Dependencies: 
// 
// Revision:
// Revision 0.01 - File Created
// Additional Comments:
// 
//////////////////////////////////////////////////////////////////////////////////


module Cache_memory(
    input [15:0] data_in,
    input [11:0] write_adr,
    
    input [11:0] read_adr,
    output logic [15:0] read_data,
    
    input clk,
    input write
    );
    
reg [15:0] MEM [0:4095];

always @(posedge clk) begin
if(write)begin
    MEM[write_adr] <= data_in;
    end
read_data <= MEM[read_adr];
end
endmodule

RAM.sv
`timescale 1ns / 1ps

module RAM(
    input logic [15:0] axi_data_in,
    input logic [11:0] axi_adr_in,
    input logic axi_write,
    input logic axi_read,
    output logic [31:0] axi_data_out,
    
    input logic [31:0] SEND_DATA,
    input logic [11:0] SEND_ADDR,

    input logic [11:0] READ_ADDRESS,
    
    output logic [15:0] READ_DATA,
    //
    input write_to_cache,
    //
    
    input logic mode,
    input logic clk
    );
 
 reg [31:0] MEM [0:4095];
 
/*always @(posedge clk) begin
    if(mode) begin
        if(axi_write)begin
           MEM[axi_adr_in] <= axi_data_in;
           READ_DATA <= MEM[READ_ADDRESS]; // need changes
        end
        else if(axi_read) axi_data_out <= MEM[axi_adr_in];
    end
    else begin
        MEM[SEND_ADDR] <= SEND_DATA;
    end
 end   */
    
    always @(posedge clk) begin
    if(mode) begin
        if(axi_write)begin
           MEM[axi_adr_in] <= axi_data_in;
        end
        else if(axi_read) axi_data_out <= MEM[axi_adr_in];
    end
    else if(write_to_cache)
                   READ_DATA <= MEM[READ_ADDRESS]; 
    else begin
        MEM[SEND_ADDR] <= SEND_DATA;
    end
 end   
endmodule

Axi_Bridge_fsm.sv
package Axi_Bridge_fsm;
  typedef enum logic [2:0] {  
    bridge_IDLE = 3'b000,
    bridge_ADDR_WRITE,
    bridge_DATA_WRITE,
    bridge_WRITE_RESPONSE,
    bridge_WAIT,
    bridge_ADDR_READ,
    bridge_DATA_READ
  } bridge_fsm;
endpackage

Axi_Bridge.sv
`include "Axi_Bridge_fsm.sv"
import Axi_Bridge_fsm::*;
module Axi_Bridge #(
  parameter DATA_WIDTH = 32
)
(
  input i_clk, i_rstn,
  input [DATA_WIDTH-1:0] i_ARDATA, i_DATA_FROM_RAM,
  input i_ARVALID, i_AWREADY, i_CALC_END,
  input [11:0] i_SAMPLES_NUMBER,
  output logic o_ARREADY, o_AWVALID, o_DATA_LOADED,
  output logic [DATA_WIDTH-1:0] o_AWDATA, o_SAMPLE_ram,
  output logic [1:0] o_AWBURST, o_ARBURST,
  output logic [11:0] o_SAMPLE_INDEX_ram,
  output logic o_WRITE_ram, o_READ_ram
  //output bridge_fsm current_state
);

bridge_fsm state, next_state;
logic [11:0] index_cnt;
bit cnt_en, cnt_clr;

// FSM
always_ff @(posedge i_clk or negedge i_rstn) begin : p_fsm_sync
  if (~i_rstn) begin
    state <= bridge_IDLE;
    index_cnt <= '0;
  end
  else begin
    state <= next_state;
    if(cnt_clr) begin
      index_cnt <= '0;
    end
    else if(cnt_en) begin
      index_cnt <= index_cnt + 1; //tu chyba bedzie ARBURST
    end
  end
end : p_fsm_sync

always_comb begin : p_fsm_comb
  {o_ARREADY, o_AWVALID, o_WRITE_ram, o_READ_ram, o_DATA_LOADED} = 5'b00000;
  {cnt_clr, cnt_en} = 2'b00;
  {o_AWDATA, o_SAMPLE_ram, o_AWBURST, o_ARBURST, o_SAMPLE_INDEX_ram} = 'x;
  case(state)
    bridge_IDLE : begin
      o_ARREADY = 1'b1;
      if(i_ARVALID) begin
        next_state = bridge_READ;
      end
    end

    bridge_READ : begin //Odczyt próbek z wejscia
      o_ARREADY = 1'b1;
      o_WRITE_ram = 1'b1;
      o_SAMPLE_INDEX_ram = index_cnt;
      o_SAMPLE_ram = i_ARDATA;
      //o_ARBURST = ?? TODO
      if(index_cnt == (i_SAMPLES_NUMBER - 1)) begin
        o_DATA_LOADED = 1'b1;
        next_state = bridge_WAIT;
        cnt_clr = 1'b1;
      end
      else if(i_ARVALID) begin
        cnt_en = 1'b1;
      end
    end

    bridge_WAIT : begin
      o_AWVALID = 1'b1;
      if(i_CALC_END && i_AWREADY) begin
        next_state = bridge_WRITE;
      end
    end

    bridge_WRITE : begin
      o_AWVALID = 1'b1;
      o_READ_ram = 1'b1;
      o_SAMPLE_INDEX_ram = index_cnt;
      o_AWDATA = i_DATA_FROM_RAM;
      if (index_cnt == (i_SAMPLES_NUMBER - 1)) begin
        cnt_clr = 1'b1;
        next_state = bridge_IDLE;
      end
      else if (i_AWREADY) begin
        cnt_en = 1'b1;
      end
    end

    default : next_state = bridge_IDLE;
  endcase
end : p_fsm_comb

//assign current_state = state; //current state at the output

endmodule

top_fft.sv
`include "RAM.sv"
`include "MUL_UNIT.sv"
`include "Rounding_unit.sv"
`include "Accumulation_unit.sv"
`include "Axi_Bridge.sv"
`include "counter.sv"
`include "fsm.sv"
`include "twidle_fac_gen.sv"
`include "Cache_memory.sv"
/////////////////////////////////////////////////////////
// Missing things:


module top_fft #(parameter N = 2)(
    // AXI BUS
    input               [15:0]  RDATA,
    input                       RVALID,
    output logic                RREADY,
    output logic        [N-1:0] RBURST,
    output logic        [31:0]  WDATA,
    output logic                WVALID,
    input logic                 WREADY,
    output logic        [N-1:0] WBURST,


    input [11:0] SAMP_NUMBER,
    input clk,
    input MAC_nRADIX,
    input n_Reset
);


logic [15:0] CACHE_DATA_IN;
logic [15:0] CACHE_DATA_OUT;
logic [15:0] TW_VAL_REAL;
logic [15:0] TW_VAL_IMAG;
logic [31:0] ACUMULATION_INPUT;
logic [31:0] MUL_REAL_RESULT;
logic [31:0] MUL_IMAG_RESULT;
logic [31:0] SEND_DATA;
logic [11:0] SEND_ADDR;

logic [11:0] N_INDEX;
logic l_nComp;
logic CALC_END;
logic counter_n_en;
logic counter_k_en;
logic counter_n_ovf;
logic device_clear;

logic [15:0] RAM_in_axi;
logic [31:0] DATA_FROM_RAM;
logic [11:0] SAMPLE_INDEX_ram;
logic READ_ram;
logic WRITE_ram;
logic LOADED_DATA;

//
logic ram_to_cache;
logic [1:0] fsm_state;

Axi_Bridge slave(.i_clk(clk), .i_rstn(n_Reset), .i_ARDATA(RDATA),
        .i_DATA_FROM_RAM(DATA_FROM_RAM), .i_ARVALID(RVALID), .i_AWREADY(WREADY),
        .i_CALC_END(CALC_END), .i_SAMPLES_NUMBER(SAMP_NUMBER),
        .o_ARREADY(RREADY), .o_AWVALID(WVALID), .o_DATA_LOADED(LOADED_DATA), 
        .o_AWDATA(WDATA), .o_SAMPLE_ram(RAM_in_axi), .o_AWBURST(WBURST), 
        .o_ARBURST(RBURST), .o_SAMPLE_INDEX_ram(SAMPLE_INDEX_ram),
        .o_WRITE_ram(WRITE_ram), .o_READ_ram(READ_ram)
);

RAM ram1(
        .axi_data_in(RAM_in_axi), 
         .axi_adr_in(SAMPLE_INDEX_ram), 
         .axi_write(WRITE_ram),
         .axi_read(READ_ram),
         .axi_data_out(DATA_FROM_RAM),
         .SEND_DATA(SEND_DATA),
         .SEND_ADDR(SEND_ADDR),
         .READ_ADDRESS(N_INDEX),
         .READ_DATA(CACHE_DATA_IN),
         //
        .write_to_cache(ram_to_cache),
         //
         .mode(l_nComp), // '1' AXI write and read, load to cache, '0' Circiut write
         .clk(clk)
);

Cache_memory c_mem(
        .data_in(CACHE_DATA_IN),
        .write_adr(N_INDEX),
        .read_adr(N_INDEX),
        .read_data(CACHE_DATA_OUT),
        .clk(clk),
        .write(ram_to_cache)
);

MUL_UNIT mul_real(
        .a_val(CACHE_DATA_OUT),
        .b_val(TW_VAL_REAL),
        .result(MUL_REAL_RESULT)
);

MUL_UNIT mul_imag(
        .a_val(CACHE_DATA_OUT),
        .b_val(TW_VAL_IMAG),
        .result(MUL_IMAG_RESULT)
);

Rounding_unit round_real(
        .val_in(MUL_REAL_RESULT),
        .val_out(ACUMULATION_INPUT[31:16])
);

Rounding_unit round_imag(
        .val_in(MUL_IMAG_RESULT),
        .val_out(ACUMULATION_INPUT[15:0])
);

Accumulation_unit acumulation(
        .val_a(ACUMULATION_INPUT),
        .val_out(SEND_DATA),
        .clk(clk),
        .ce(counter_k_en),
        .nrst(device_clear)
);

counter n_counter(
        .clk(clk), 
        .ce(counter_n_en), 
        .nrst(device_clear), 
        .max_val(SAMP_NUMBER), 
        .o_data(N_INDEX), 
        .over(counter_n_ovf)
);

counter k_counter(
        .clk(clk), 
        .ce(counter_k_en & counter_n_ovf), 
        .nrst(device_clear), 
        .max_val(SAMP_NUMBER), 
        .o_data(SEND_ADDR), 
        .over(CALC_END)
);

fsm finit_state(
        .clk(clk),
        .ce(MAC_nRADIX),
        .nrst(n_Reset),
        .sample_num(SAMP_NUMBER),
        .data_loaded(LOADED_DATA),
        .calc_end(CALC_END),
        .load_nCompute(l_nComp),
        .count_n_en(counter_n_en),
        .count_k_en(counter_k_en),
        .clear(device_clear),
        //
        .load_to_cache(ram_to_cache),
        //
        .data_to_cache_loaded(counter_n_ovf),
        .state(fsm_state)

);

twiddle_rom tw_gen(
        .N(SAMP_NUMBER), 
        .k_index(SEND_ADDR), 
        .n_index(N_INDEX), 
        .data({TW_VAL_REAL,TW_VAL_IMAG})
);

endmodule : top_fft

top_fft_tb.sv
`include "top_fft.sv"

module top_fft_tb;
parameter DATA_WIDTH = 32;
// Inputs
logic i_clk, i_rstn;
logic [15:0] i_ARDATA; 
logic [31:0] i_DATA_FROM_RAM;
logic i_ARVALID, i_AWREADY, i_CALC_END;
logic [11:0] i_SAMPLES_NUMBER;
// Outputs
logic o_ARREADY, o_AWVALID, o_DATA_LOADED;
logic [DATA_WIDTH-1:0] o_AWDATA;
logic [15:0] o_SAMPLE_ram;
logic [1:0] o_AWBURST, o_ARBURST;
logic [11:0] o_SAMPLE_INDEX_ram;
logic o_WRITE_ram, o_READ_ram;
bridge_fsm current_state;

//
logic MAC_nRADIX;

top_fft dut(
    .clk(i_clk),
    .n_Reset(i_rstn),
    .MAC_nRADIX(MAC_nRADIX),
    .SAMP_NUMBER(i_SAMPLES_NUMBER),
    .RDATA(i_ARDATA),
    .RVALID(i_ARVALID),
    .RREADY(o_ARREADY),
    .RBURST(o_ARBURST),
    .WDATA(o_AWDATA),
    .WVALID(o_AWVALID),
    .WREADY(i_AWREADY),
    .WBURST(o_AWBURST)
);

initial begin
    MAC_nRADIX = 1'b1;
    i_clk = 1'b0; i_rstn = 1'b0;
    i_ARDATA = '0; 
    //i_DATA_FROM_RAM = '0;
    i_SAMPLES_NUMBER = '0;
    forever #5 i_clk = ~i_clk;
end

always @(posedge i_clk) begin
    i_ARDATA += 1;
    //i_DATA_FROM_RAM += 2;
end

initial begin

    @(negedge i_clk);
    i_rstn = 1'b1;
    @(posedge i_clk);
    // READ
    i_SAMPLES_NUMBER = 10;
    i_ARVALID = 1'b1;
    repeat(i_SAMPLES_NUMBER) @(posedge i_clk);
    // WAIT
    i_ARVALID = 1'b0;
    i_AWREADY = 1'b1;
    @(posedge i_clk);
    @(posedge i_clk);
    #500 $finish;
end

initial begin
    $dumpfile("top.vcd");
    $dumpvars;
    $dumpon;
end

endmodule

top.vcd
$date
	Tue Dec 17 20:04:18 2024
$end
$version
	Icarus Verilog
$end
$timescale
	1ps
$end
$scope module top_fft_tb $end
$var wire 1 ! o_AWVALID $end
$var wire 32 " o_AWDATA [31:0] $end
$var wire 2 # o_AWBURST [1:0] $end
$var wire 1 $ o_ARREADY $end
$var wire 2 % o_ARBURST [1:0] $end
$var parameter 32 & DATA_WIDTH $end
$var reg 1 ' MAC_nRADIX $end
$var reg 16 ( i_ARDATA [15:0] $end
$var reg 1 ) i_ARVALID $end
$var reg 1 * i_AWREADY $end
$var reg 12 + i_SAMPLES_NUMBER [11:0] $end
$var reg 1 , i_clk $end
$var reg 1 - i_rstn $end
$scope module dut $end
$var wire 1 ' MAC_nRADIX $end
$var wire 16 . RDATA [15:0] $end
$var wire 1 ) RVALID $end
$var wire 12 / SAMP_NUMBER [11:0] $end
$var wire 1 * WREADY $end
$var wire 1 , clk $end
$var wire 1 - n_Reset $end
$var wire 1 0 ram_to_cache $end
$var wire 1 1 l_nComp $end
$var wire 2 2 fsm_state [1:0] $end
$var wire 1 3 device_clear $end
$var wire 1 4 counter_n_ovf $end
$var wire 1 5 counter_n_en $end
$var wire 1 6 counter_k_en $end
$var wire 1 ! WVALID $end
$var wire 1 7 WRITE_ram $end
$var wire 32 8 WDATA [31:0] $end
$var wire 2 9 WBURST [1:0] $end
$var wire 16 : TW_VAL_REAL [15:0] $end
$var wire 16 ; TW_VAL_IMAG [15:0] $end
$var wire 32 < SEND_DATA [31:0] $end
$var wire 12 = SEND_ADDR [11:0] $end
$var wire 12 > SAMPLE_INDEX_ram [11:0] $end
$var wire 1 $ RREADY $end
$var wire 1 ? READ_ram $end
$var wire 2 @ RBURST [1:0] $end
$var wire 16 A RAM_in_axi [15:0] $end
$var wire 12 B N_INDEX [11:0] $end
$var wire 32 C MUL_REAL_RESULT [31:0] $end
$var wire 32 D MUL_IMAG_RESULT [31:0] $end
$var wire 1 E LOADED_DATA $end
$var wire 32 F DATA_FROM_RAM [31:0] $end
$var wire 1 G CALC_END $end
$var wire 16 H CACHE_DATA_OUT [15:0] $end
$var wire 16 I CACHE_DATA_IN [15:0] $end
$var wire 32 J ACUMULATION_INPUT [31:0] $end
$var parameter 32 K N $end
$scope module acumulation $end
$var wire 1 , clk $end
$var wire 32 L val_a [31:0] $end
$var wire 1 3 nrst $end
$var wire 1 6 ce $end
$var reg 16 M accumulated_val_imag [15:0] $end
$var reg 16 N accumulated_val_real [15:0] $end
$var reg 32 O val_out [31:0] $end
$upscope $end
$scope module c_mem $end
$var wire 1 , clk $end
$var wire 12 P write_adr [11:0] $end
$var wire 1 0 write $end
$var wire 12 Q read_adr [11:0] $end
$var wire 16 R data_in [15:0] $end
$var reg 16 S read_data [15:0] $end
$upscope $end
$scope module finit_state $end
$var wire 1 ' ce $end
$var wire 1 , clk $end
$var wire 1 - nrst $end
$var wire 12 T sample_num [11:0] $end
$var wire 2 U state [1:0] $end
$var wire 1 4 data_to_cache_loaded $end
$var wire 1 E data_loaded $end
$var wire 1 G calc_end $end
$var parameter 2 V CLEAR $end
$var parameter 2 W COMPUTE $end
$var parameter 2 X IDLE $end
$var parameter 2 Y LOAD_TO_CACHE $end
$var reg 1 3 clear $end
$var reg 1 6 count_k_en $end
$var reg 1 5 count_n_en $end
$var reg 1 1 load_nCompute $end
$var reg 1 0 load_to_cache $end
$var reg 2 Z states [1:0] $end
$upscope $end
$scope module k_counter $end
$var wire 1 [ ce $end
$var wire 1 , clk $end
$var wire 12 \ max_val [11:0] $end
$var wire 1 3 nrst $end
$var reg 12 ] coun_val [11:0] $end
$var reg 12 ^ o_data [11:0] $end
$var reg 1 G over $end
$upscope $end
$scope module mul_imag $end
$var wire 16 _ a_val [15:0] $end
$var wire 16 ` b_val [15:0] $end
$var reg 32 a result [31:0] $end
$upscope $end
$scope module mul_real $end
$var wire 16 b a_val [15:0] $end
$var wire 16 c b_val [15:0] $end
$var reg 32 d result [31:0] $end
$upscope $end
$scope module n_counter $end
$var wire 1 5 ce $end
$var wire 1 , clk $end
$var wire 12 e max_val [11:0] $end
$var wire 1 3 nrst $end
$var reg 12 f coun_val [11:0] $end
$var reg 12 g o_data [11:0] $end
$var reg 1 4 over $end
$upscope $end
$scope module ram1 $end
$var wire 12 h READ_ADDRESS [11:0] $end
$var wire 12 i SEND_ADDR [11:0] $end
$var wire 32 j SEND_DATA [31:0] $end
$var wire 1 , clk $end
$var wire 1 1 mode $end
$var wire 1 0 write_to_cache $end
$var wire 1 7 axi_write $end
$var wire 1 ? axi_read $end
$var wire 16 k axi_data_in [15:0] $end
$var wire 12 l axi_adr_in [11:0] $end
$var reg 16 m READ_DATA [15:0] $end
$var reg 32 n axi_data_out [31:0] $end
$upscope $end
$scope module round_imag $end
$var wire 32 o val_in [31:0] $end
$var wire 16 p val_out [15:0] $end
$upscope $end
$scope module round_real $end
$var wire 32 q val_in [31:0] $end
$var wire 16 r val_out [15:0] $end
$upscope $end
$scope module slave $end
$var wire 16 s i_ARDATA [15:0] $end
$var wire 1 ) i_ARVALID $end
$var wire 1 * i_AWREADY $end
$var wire 1 G i_CALC_END $end
$var wire 32 t i_DATA_FROM_RAM [31:0] $end
$var wire 12 u i_SAMPLES_NUMBER [11:0] $end
$var wire 1 , i_clk $end
$var wire 1 - i_rstn $end
$var parameter 32 v DATA_WIDTH $end
$var reg 12 w index_cnt [11:0] $end
$var reg 2 x next_state [1:0] $end
$var reg 2 y o_ARBURST [1:0] $end
$var reg 1 $ o_ARREADY $end
$var reg 2 z o_AWBURST [1:0] $end
$var reg 32 { o_AWDATA [31:0] $end
$var reg 1 ! o_AWVALID $end
$var reg 1 E o_DATA_LOADED $end
$var reg 1 ? o_READ_ram $end
$var reg 12 | o_SAMPLE_INDEX_ram [11:0] $end
$var reg 16 } o_SAMPLE_ram [15:0] $end
$var reg 1 7 o_WRITE_ram $end
$var reg 2 ~ state [1:0] $end
$var reg 1 !" cnt_clr $end
$var reg 1 "" cnt_en $end
$scope begin p_fsm_comb $end
$upscope $end
$scope begin p_fsm_sync $end
$upscope $end
$upscope $end
$scope module tw_gen $end
$var wire 12 #" N [11:0] $end
$var wire 12 $" k_index [11:0] $end
$var wire 12 %" n_index [11:0] $end
$var parameter 32 &" DEPTH $end
$var parameter 32 '" WIDTH $end
$var reg 12 (" addr [11:0] $end
$var reg 32 )" data [31:0] $end
$upscope $end
$upscope $end
$upscope $end
$enddefinitions $end
$comment Show the parameter values. $end
$dumpall
b100000 '"
b1000000000000 &"
b100000 v
b1 Y
b0 X
b11 W
b10 V
b10 K
b100000 &
$end
#0
$dumpvars
bx )"
bx ("
bx %"
bx $"
b0 #"
0""
0!"
b0 ~
bx }
bx |
bx {
bx z
bx y
b0 x
b0 w
b0 u
bx t
b0 s
bx r
bx q
bx p
bx o
bx n
bx m
bx l
bx k
bx j
bx i
bx h
bx g
bx f
b0 e
bx d
bx c
bx b
bx a
bx `
bx _
bx ^
bx ]
b0 \
x[
bx Z
bx U
b0 T
bx S
bx R
bx Q
bx P
bx O
bx N
bx M
bx L
bx J
bx I
bx H
xG
bx F
0E
bx D
bx C
bx B
bx A
bx @
0?
bx >
bx =
bx <
bx ;
bx :
bx 9
bx 8
07
x6
x5
x4
x3
bx 2
x1
x0
b0 /
b0 .
0-
0,
b0 +
x*
x)
b0 (
1'
bx %
1$
bx #
bx "
0!
$end
#5000
0G
0[
04
00
03
06
05
11
b0 2
b0 U
b0 Z
1$
b1 (
b1 .
b1 s
1,
#10000
1-
0,
#15000
b0 ;
b0 `
b111111111111111 :
b111111111111111 c
b1111111111111110000000000000000 )"
b0 ("
b0 =
b0 ^
b0 i
b0 $"
b0 B
b0 P
b0 Q
b0 g
b0 h
b0 %"
b0 <
b0 O
b0 j
b0 ]
b0 f
b0 M
b0 N
b1 x
1$
b10 (
b10 .
b10 s
1)
b1010 +
b1010 /
b1010 T
b1010 \
b1010 e
b1010 u
b1010 #"
1,
#20000
0,
#25000
1""
b11 A
b11 k
b11 }
b0 >
b0 l
b0 |
17
b1 ~
1$
b11 (
b11 .
b11 s
1,
#30000
0,
#35000
b1 w
b100 A
b100 k
b100 }
b1 >
b1 l
b1 |
1""
1$
17
b100 (
b100 .
b100 s
1,
#40000
0,
#45000
b10 w
b101 A
b101 k
b101 }
b10 >
b10 l
b10 |
1""
1$
17
b101 (
b101 .
b101 s
1,
#50000
0,
#55000
b11 w
b110 A
b110 k
b110 }
b11 >
b11 l
b11 |
1""
1$
17
b110 (
b110 .
b110 s
1,
#60000
0,
#65000
b100 w
b111 A
b111 k
b111 }
b100 >
b100 l
b100 |
1""
1$
17
b111 (
b111 .
b111 s
1,
#70000
0,
#75000
b101 w
b1000 A
b1000 k
b1000 }
b101 >
b101 l
b101 |
1""
1$
17
b1000 (
b1000 .
b1000 s
1,
#80000
0,
#85000
b110 w
b1001 A
b1001 k
b1001 }
b110 >
b110 l
b110 |
1""
1$
17
b1001 (
b1001 .
b1001 s
1,
#90000
0,
#95000
b111 w
b1010 A
b1010 k
b1010 }
b111 >
b111 l
b111 |
1""
1$
17
b1010 (
b1010 .
b1010 s
1,
#100000
0,
#105000
b1000 w
b1011 A
b1011 k
b1011 }
b1000 >
b1000 l
b1000 |
1""
1$
17
b1011 (
b1011 .
b1011 s
1,
#110000
0,
#115000
1!"
b11 x
1E
b1001 w
b1100 A
b1100 k
b1100 }
b1001 >
b1001 l
b1001 |
0""
1$
17
b1100 (
b1100 .
b1100 s
1*
0)
1,
#120000
0,
#125000
1!
b0 w
b11 ~
bx A
bx k
bx }
bx >
bx l
bx |
0!"
0$
07
b1101 (
b1101 .
b1101 s
0E
1,
#130000
0,
#135000
1!
b1110 (
b1110 .
b1110 s
1,
#140000
0,
#145000
1!
b1111 (
b1111 .
b1111 s
1,
#150000
0,
#155000
1!
b10000 (
b10000 .
b10000 s
1,
#160000
0,
#165000
1!
b10001 (
b10001 .
b10001 s
1,
#170000
0,
#175000
1!
b10010 (
b10010 .
b10010 s
1,
#180000
0,
#185000
1!
b10011 (
b10011 .
b10011 s
1,
#190000
0,
#195000
1!
b10100 (
b10100 .
b10100 s
1,
#200000
0,
#205000
1!
b10101 (
b10101 .
b10101 s
1,
#210000
0,
#215000
1!
b10110 (
b10110 .
b10110 s
1,
#220000
0,
#225000
1!
b10111 (
b10111 .
b10111 s
1,
#230000
0,
#235000
1!
b11000 (
b11000 .
b11000 s
1,
#240000
0,
#245000
1!
b11001 (
b11001 .
b11001 s
1,
#250000
0,
#255000
1!
b11010 (
b11010 .
b11010 s
1,
#260000
0,
#265000
1!
b11011 (
b11011 .
b11011 s
1,
#270000
0,
#275000
1!
b11100 (
b11100 .
b11100 s
1,
#280000
0,
#285000
1!
b11101 (
b11101 .
b11101 s
1,
#290000
0,
#295000
1!
b11110 (
b11110 .
b11110 s
1,
#300000
0,
#305000
1!
b11111 (
b11111 .
b11111 s
1,
#310000
0,
#315000
1!
b100000 (
b100000 .
b100000 s
1,
#320000
0,
#325000
1!
b100001 (
b100001 .
b100001 s
1,
#330000
0,
#335000
1!
b100010 (
b100010 .
b100010 s
1,
#340000
0,
#345000
1!
b100011 (
b100011 .
b100011 s
1,
#350000
0,
#355000
1!
b100100 (
b100100 .
b100100 s
1,
#360000
0,
#365000
1!
b100101 (
b100101 .
b100101 s
1,
#370000
0,
#375000
1!
b100110 (
b100110 .
b100110 s
1,
#380000
0,
#385000
1!
b100111 (
b100111 .
b100111 s
1,
#390000
0,
#395000
1!
b101000 (
b101000 .
b101000 s
1,
#400000
0,
#405000
1!
b101001 (
b101001 .
b101001 s
1,
#410000
0,
#415000
1!
b101010 (
b101010 .
b101010 s
1,
#420000
0,
#425000
1!
b101011 (
b101011 .
b101011 s
1,
#430000
0,
#435000
1!
b101100 (
b101100 .
b101100 s
1,
#440000
0,
#445000
1!
b101101 (
b101101 .
b101101 s
1,
#450000
0,
#455000
1!
b101110 (
b101110 .
b101110 s
1,
#460000
0,
#465000
1!
b101111 (
b101111 .
b101111 s
1,
#470000
0,
#475000
1!
b110000 (
b110000 .
b110000 s
1,
#480000
0,
#485000
1!
b110001 (
b110001 .
b110001 s
1,
#490000
0,
#495000
1!
b110010 (
b110010 .
b110010 s
1,
#500000
0,
#505000
1!
b110011 (
b110011 .
b110011 s
1,
#510000
0,
#515000
1!
b110100 (
b110100 .
b110100 s
1,
#520000
0,
#525000
1!
b110101 (
b110101 .
b110101 s
1,
#530000
0,
#535000
1!
b110110 (
b110110 .
b110110 s
1,
#540000
0,
#545000
1!
b110111 (
b110111 .
b110111 s
1,
#550000
0,
#555000
1!
b111000 (
b111000 .
b111000 s
1,
#560000
0,
#565000
1!
b111001 (
b111001 .
b111001 s
1,
#570000
0,
#575000
1!
b111010 (
b111010 .
b111010 s
1,
#580000
0,
#585000
1!
b111011 (
b111011 .
b111011 s
1,
#590000
0,
#595000
1!
b111100 (
b111100 .
b111100 s
1,
#600000
0,
#605000
1!
b111101 (
b111101 .
b111101 s
1,
#610000
0,
#615000
1!
b111110 (
b111110 .
b111110 s
1,
#620000
0,
#625000
1!
b111111 (
b111111 .
b111111 s
1,
#630000
0,
#635000
1!
b1000000 (
b1000000 .
b1000000 s
1,
