RAM.sv
`timescale 1ns / 1ps

module RAM(
    input logic [15:0] axi_data_in,
    input logic [11:0] axi_adr_in,
    input logic axi_write,
    input logic axi_read,
    output logic [31:0] axi_data_out,
    
    input logic [31:0] SEND_DATA,
    input logic [11:0] SEND_ADDR,

    input logic [11:0] READ_ADDRESS,
    
    output logic [15:0] READ_DATA,
    //
    input write_to_cache,
    //
    
    input logic mode,
    input logic clk
    );
 
 reg [31:0] MEM [0:4095];
 
/*always @(posedge clk) begin
    if(mode) begin
        if(axi_write)begin
           MEM[axi_adr_in] <= axi_data_in;
           READ_DATA <= MEM[READ_ADDRESS]; // need changes
        end
        else if(axi_read) axi_data_out <= MEM[axi_adr_in];
    end
    else begin
        MEM[SEND_ADDR] <= SEND_DATA;
    end
 end   */
    
    always @(posedge clk) begin
    if(mode) begin
        if(axi_write)begin
           MEM[axi_adr_in] <= axi_data_in;
        end
        else if(axi_read) axi_data_out <= MEM[axi_adr_in];
    end
    else if(write_to_cache)
        READ_DATA <= MEM[READ_ADDRESS]; 
    else begin
        MEM[SEND_ADDR] <= SEND_DATA;
    end
 end   
endmodule

Axi_Bridge_fsm.sv
package Axi_Bridge_fsm;
  typedef enum logic [2:0] {  
    bridge_IDLE = 3'b000,
    bridge_ADDR_WRITE,
    bridge_DATA_WRITE,
    bridge_WRITE_RESPONSE,
    bridge_WAIT,
    bridge_ADDR_READ,
    bridge_DATA_READ
  } bridge_fsm;
endpackage

Axi_Bridge.sv
//`include "Axi_Bridge_fsm.sv"
import Axi_Bridge_fsm::*;
module Axi_Bridge #(
  parameter DATA_WIDTH = 32
)
(
  input i_clk, i_rstn,
  input [15:0] i_AWDATA, 
  input [DATA_WIDTH-1:0] i_DATA_FROM_RAM,
  input i_AWVALID, i_ARREADY, i_CALC_END,
  input [11:0] i_SAMPLES_NUMBER,
  output logic o_AWREADY, o_ARVALID, o_DATA_LOADED,
  output logic [DATA_WIDTH-1:0] o_ARDATA, 
  output logic [15:0] o_SAMPLE_ram,
  output logic [1:0] o_AWBURST, o_ARBURST,
  output logic [11:0] o_SAMPLE_INDEX_ram,
  output logic o_WRITE_ram, o_READ_ram
  //output bridge_fsm current_state // - ZAKOMENTOWAC
);

bridge_fsm state, next_state;
logic [11:0] index_cnt;
bit cnt_en, cnt_clr;

// FSM
always_ff @(posedge i_clk or negedge i_rstn) begin : p_fsm_sync
  if (~i_rstn) begin
    state <= bridge_IDLE;
    index_cnt <= '0;
  end
  else begin
    state <= next_state;
    if(cnt_clr) begin
      index_cnt <= '0;
    end
    else if(cnt_en) begin
      index_cnt <= index_cnt + 1; //tu chyba bedzie ARBURST
    end
  end
end : p_fsm_sync

always_comb begin : p_fsm_comb
  {o_AWREADY, o_ARVALID, o_WRITE_ram, o_READ_ram, o_DATA_LOADED} = 5'b00000;
  {cnt_clr, cnt_en} = 2'b00;
  {o_ARDATA, o_SAMPLE_ram, o_AWBURST, o_ARBURST, o_SAMPLE_INDEX_ram} = 'x;
  case(state)
    bridge_IDLE : begin
   
      o_AWREADY = 1'b1;
      if(i_AWVALID) begin
        next_state = bridge_WRITE;
      end
    end

    bridge_WRITE : begin //Zapis probek do RAMU
      o_AWREADY = 1'b1;
      o_WRITE_ram = 1'b1;
      o_SAMPLE_INDEX_ram = index_cnt;
      //o_SAMPLE_ram = o_ARDATA;
      o_SAMPLE_ram = i_AWDATA;
      //o_ARBURST = ?? TODO
      if(index_cnt == (i_SAMPLES_NUMBER - 1)) begin
        o_DATA_LOADED = 1'b1; 
        next_state = bridge_WAIT;
        cnt_clr = 1'b1;
      end
      else if(i_AWVALID) begin
        cnt_en = 1'b1;
      end
    end

    bridge_WAIT : begin
      if(i_CALC_END && i_ARREADY) begin
        next_state = bridge_READ;
      end
    end

    bridge_READ : begin
      o_ARVALID = 1'b1;
      o_READ_ram = 1'b1;
      o_SAMPLE_INDEX_ram = index_cnt;
      o_ARDATA = i_DATA_FROM_RAM;
      if (index_cnt == (i_SAMPLES_NUMBER)) begin
        cnt_clr = 1'b1;
        next_state = bridge_IDLE;
        o_ARVALID = 1'b0;
      end
      else if (i_ARREADY) begin
        cnt_en = 1'b1;
      end
    end

    default : next_state = bridge_IDLE;
  endcase
end : p_fsm_comb

assign current_state = state; //current state at the output, zakomentowac

endmodule

top_axi_lite.sv
module top_axi_lite;
    logic [31:0] RDATA;
    logic RVALID;
    logic RREADY;
    logic [1:0] RBURST;
    logic [15:0]  WDATA;
    logic WVALID;
    logic WREADY;
    logic [1:0] WBURST;
    logic [11:0] SAMP_NUMBER;
    logic clk;
    logic n_Reset;

logic [31:0] DATA_FROM_RAM;
logic [15:0] RAM_in_axi;
logic [11:0] SAMPLE_INDEX_ram;
logic CALC_END;
logic WRITE_TO_CACHE;

 

Axi_Bridge slave(.i_clk(clk), .i_rstn(n_Reset), .i_AWDATA(WDATA),
        .i_DATA_FROM_RAM(DATA_FROM_RAM), .i_AWVALID(WVALID), .i_ARREADY(RREADY),
        .i_CALC_END(CALC_END), .i_SAMPLES_NUMBER(SAMP_NUMBER),
        .o_AWREADY(WREADY), .o_ARVALID(RVALID), .o_DATA_LOADED(LOADED_DATA), 
        .o_ARDATA(RDATA), .o_SAMPLE_ram(RAM_in_axi), .o_AWBURST(WBURST), 
        .o_ARBURST(RBURST), .o_SAMPLE_INDEX_ram(SAMPLE_INDEX_ram),
        .o_WRITE_ram(WRITE_ram), .o_READ_ram(READ_ram)
);

RAM ram1(
        .axi_data_in(RAM_in_axi), 
         .axi_adr_in(SAMPLE_INDEX_ram), 
         .axi_write(WRITE_ram),
         .axi_read(READ_ram),
         .axi_data_out(DATA_FROM_RAM),
         .SEND_DATA(),
         .SEND_ADDR(),
         .READ_ADDRESS(),
         .READ_DATA(),
         //
         .write_to_cache(WRITE_TO_CACHE),
         //
         .mode(1'b1), // '1' AXI write and read, load to cache, '0' Circiut write
         .clk(clk)
);

initial begin
    $dumpon;
    $dumpvars;
    $dumpfile("top_axi_lite.vcd");
end
endmodule

verif/dump.vcd
$date
	Sun Jan 12 15:28:06 2025
$end
$version
	Icarus Verilog
$end
$timescale
	1ps
$end
$scope module top_axi_lite $end
$var wire 1 ! WRITE_ram $end
$var wire 1 " WREADY $end
$var wire 2 # WBURST [1:0] $end
$var wire 12 $ SAMPLE_INDEX_ram [11:0] $end
$var wire 1 % RVALID $end
$var wire 1 & READ_ram $end
$var wire 32 ' RDATA [31:0] $end
$var wire 2 ( RBURST [1:0] $end
$var wire 16 ) RAM_in_axi [15:0] $end
$var wire 1 * LOADED_DATA $end
$var wire 32 + DATA_FROM_RAM [31:0] $end
$var reg 1 , CALC_END $end
$var reg 1 - RREADY $end
$var reg 12 . SAMP_NUMBER [11:0] $end
$var reg 16 / WDATA [15:0] $end
$var reg 1 0 WRITE_TO_CACHE $end
$var reg 1 1 WVALID $end
$var reg 1 2 clk $end
$var reg 1 3 n_Reset $end
$scope module ram1 $end
$var wire 12 4 READ_ADDRESS [11:0] $end
$var wire 12 5 SEND_ADDR [11:0] $end
$var wire 32 6 SEND_DATA [31:0] $end
$var wire 1 2 clk $end
$var wire 1 7 mode $end
$var wire 1 0 write_to_cache $end
$var wire 1 ! axi_write $end
$var wire 1 & axi_read $end
$var wire 16 8 axi_data_in [15:0] $end
$var wire 12 9 axi_adr_in [11:0] $end
$var reg 16 : READ_DATA [15:0] $end
$var reg 32 ; axi_data_out [31:0] $end
$upscope $end
$scope module slave $end
$var wire 1 - i_ARREADY $end
$var wire 16 < i_AWDATA [15:0] $end
$var wire 1 1 i_AWVALID $end
$var wire 1 , i_CALC_END $end
$var wire 32 = i_DATA_FROM_RAM [31:0] $end
$var wire 12 > i_SAMPLES_NUMBER [11:0] $end
$var wire 1 2 i_clk $end
$var wire 1 3 i_rstn $end
$var wire 1 ? current_state $end
$var parameter 32 @ DATA_WIDTH $end
$var reg 12 A index_cnt [11:0] $end
$var reg 2 B next_state [1:0] $end
$var reg 2 C o_ARBURST [1:0] $end
$var reg 32 D o_ARDATA [31:0] $end
$var reg 1 % o_ARVALID $end
$var reg 2 E o_AWBURST [1:0] $end
$var reg 1 " o_AWREADY $end
$var reg 1 * o_DATA_LOADED $end
$var reg 1 & o_READ_ram $end
$var reg 12 F o_SAMPLE_INDEX_ram [11:0] $end
$var reg 16 G o_SAMPLE_ram [15:0] $end
$var reg 1 ! o_WRITE_ram $end
$var reg 2 H state [1:0] $end
$var reg 1 I cnt_clr $end
$var reg 1 J cnt_en $end
$scope begin p_fsm_comb $end
$upscope $end
$scope begin p_fsm_sync $end
$upscope $end
$upscope $end
$upscope $end
$enddefinitions $end
$comment Show the parameter values. $end
$dumpall
b100000 @
$end
#0
$dumpvars
0J
0I
b0 H
bx G
bx F
bx E
bx D
bx C
b0 B
b0 A
0?
b101 >
bx =
bx <
bx ;
bx :
bx 9
bx 8
17
bz 6
bz 5
bz 4
03
12
01
00
bx /
b101 .
0-
0,
bx +
0*
bx )
bx (
bx '
0&
0%
bx $
bx #
1"
0!
$end
#5000
02
#10000
12
#15000
02
#20000
12
13
#25000
02
#30000
b1011111011101111 )
b1011111011101111 8
b1011111011101111 G
b1011111011101111 /
b1011111011101111 <
1J
b0 $
b0 9
b0 F
1!
b10 H
b10 B
1"
12
11
#35000
02
#40000
b1011101010111110 /
b1011101010111110 <
b1011101010111110 )
b1011101010111110 8
b1011101010111110 G
b1 $
b1 9
b1 F
1J
1"
1!
b1 A
12
#45000
02
#50000
b1011101010111010 /
b1011101010111010 <
b1011101010111010 )
b1011101010111010 8
b1011101010111010 G
b10 $
b10 9
b10 F
1J
1"
1!
b10 A
12
#55000
02
#60000
b1010100111000110 /
b1010100111000110 <
b1010100111000110 )
b1010100111000110 8
b1010100111000110 G
b11 $
b11 9
b11 F
1J
1"
1!
b11 A
12
#65000
02
#70000
b1101010101101010 /
b1101010101101010 <
1I
b11 B
1*
b1101010101101010 )
b1101010101101010 8
b1101010101101010 G
b100 $
b100 9
b100 F
0J
1"
1!
b100 A
12
#75000
02
#80000
1-
01
bx )
bx 8
bx G
bx $
bx 9
bx F
0I
0"
0!
0*
1?
b0 A
b11 H
12
#85000
02
#90000
12
#95000
02
#100000
b1 B
1,
12
#105000
02
#110000
1J
b0 $
b0 9
b0 F
1&
1%
b1 H
12
#115000
02
#120000
b1011111011101111 '
b1011111011101111 D
b1 $
b1 9
b1 F
1J
1%
1&
b1011111011101111 +
b1011111011101111 ;
b1011111011101111 =
b1 A
12
#125000
02
#130000
b1011101010111110 '
b1011101010111110 D
b10 $
b10 9
b10 F
1J
1%
1&
b1011101010111110 +
b1011101010111110 ;
b1011101010111110 =
b10 A
12
#135000
02
#140000
b1011101010111010 '
b1011101010111010 D
b11 $
b11 9
b11 F
1J
1%
1&
b1011101010111010 +
b1011101010111010 ;
b1011101010111010 =
b11 A
12
#145000
02
#150000
b1010100111000110 '
b1010100111000110 D
b100 $
b100 9
b100 F
1J
1%
1&
b1010100111000110 +
b1010100111000110 ;
b1010100111000110 =
b100 A
12
#155000
02
#160000
b0 B
1I
b1101010101101010 '
b1101010101101010 D
b101 $
b101 9
b101 F
0J
0%
1&
b1101010101101010 +
b1101010101101010 ;
b1101010101101010 =
b101 A
12
#165000
02
#170000
1"
bx '
bx D
bx $
bx 9
bx F
0I
0&
0?
bx +
bx ;
bx =
b0 A
b0 H
12
