RAM.sv
`timescale 1ns / 1ps

module RAM(
    input logic [15:0] axi_data_in,
    input logic [11:0] axi_adr_in,
    input logic axi_write,
    input logic axi_read,
    output logic [31:0] axi_data_out,
    
    input logic [31:0] SEND_DATA,
    input logic [11:0] SEND_ADDR,

    input logic [11:0] READ_ADDRESS,
    
    output logic [15:0] READ_DATA,
    //
    input write_to_cache,
    //
    
    input logic mode,
    input logic clk
    );
 
 reg [31:0] MEM [0:4095];
 
/*always @(posedge clk) begin
    if(mode) begin
        if(axi_write)begin
           MEM[axi_adr_in] <= axi_data_in;
           READ_DATA <= MEM[READ_ADDRESS]; // need changes
        end
        else if(axi_read) axi_data_out <= MEM[axi_adr_in];
    end
    else begin
        MEM[SEND_ADDR] <= SEND_DATA;
    end
 end   */
    
    always @(posedge clk) begin
    if(mode) begin
        if(axi_write)begin
           MEM[axi_adr_in] <= axi_data_in;
        end
        else if(axi_read) axi_data_out <= MEM[axi_adr_in];
    end
    else if(write_to_cache)
        READ_DATA <= MEM[READ_ADDRESS]; 
    else begin
        MEM[SEND_ADDR] <= SEND_DATA;
    end
 end   
endmodule

Axi_Bridge_fsm.sv
package Axi_Bridge_fsm;
  typedef enum logic [2:0] {  
    bridge_IDLE = 3'b000,
    bridge_ADDR_WRITE,
    bridge_DATA_WRITE,
    bridge_WRITE_RESPONSE,
    bridge_WAIT,
    bridge_ADDR_READ,
    bridge_DATA_READ
  } bridge_fsm;
endpackage

Axi_Bridge.sv
//`include "Axi_Bridge_fsm.sv"
import Axi_Bridge_fsm::*;
module Axi_Bridge #(
  parameter DATA_WIDTH = 32,
  parameter ID_W_WIDTH = 2, //obczaic szerokosc
  parameter ID_R_WIDTH = 2
)
(
  input i_clk, i_rstn,
  // WRITE DATA CHANNEL
  input [15:0] i_WDATA,
  input [1:0] i_WSTRB,
  input i_WVALID, i_WLAST,
  output logic o_WREADY,
  // READ DATA CHANNEL
  input i_RREADY,
  output logic [DATA_WIDTH-1:0] o_RDATA,
  output logic [ID_R_WIDTH-1:0] o_RID,
  output logic o_RVALID, o_RLAST,
  // ADDRESS WRITE CHANNEL
  input [11:0] i_AWADDR,
  input [7:0] i_AWLEN,
  input [2:0] i_AWSIZE,
  input [1:0] i_AWBURST,
  input [ID_W_WIDTH-1:0] i_AWID,
  input i_AWVALID,
  output logic o_AWREADY,
  // ADDRESS READ CHANNEL
  input [11:0] i_ARADDR,
  input [7:0] i_ARLEN,
  input [2:0] i_ARSIZE,
  input [1:0] i_ARBURST,
  input [ID_R_WIDTH-1:0] i_ARID,
  input i_ARVALID,
  output logic o_ARREADY,
  //WRITE RESPONSE CHANNEL
  input i_BREADY,
  output logic o_BVALID,
  output logic [ID_W_WIDTH-1:0] o_BID,
  // REST OF SIGNALS
  input [DATA_WIDTH-1:0] i_DATA_FROM_RAM,
  input i_CALC_END,
  input [11:0] i_SAMPLES_NUMBER,
  output logic o_DATA_LOADED,
  output logic [15:0] o_SAMPLE_ram,
  output logic [11:0] o_SAMPLE_INDEX_ram,
  output logic o_WRITE_ram, o_READ_ram
  //output bridge_fsm current_state // - ZAKOMENTOWAC
);

bridge_fsm state, next_state;
logic [11:0] index_cnt;
logic [11:0] data_in_burst_cnt;
bit cnt_en, cnt_clr;
logic [2:0] size;
logic [7:0] length;
logic [ID_W_WIDTH-1:0] trans_id;

// FSM
always_ff @(posedge i_clk or negedge i_rstn) begin : p_fsm_sync
  if (~i_rstn) begin
    state <= bridge_IDLE;
    {index_cnt, size, length} <= '0;
    data_in_burst_cnt <= '0;
    trans_id <= 'x;
  end
  else begin
    state <= next_state;
    if(cnt_clr) begin
      index_cnt <= 12'h0;
      data_in_burst_cnt <= 12'h0;
    end
    else if(cnt_en) begin
      index_cnt <= index_cnt + size; //size from AxSIZE
      data_in_burst_cnt <= data_in_burst_cnt + size;
    end                              // INCR burst addressing

    if(next_state == bridge_ADDR_WRITE && i_AWBURST == 2'b01) begin
      trans_id <= i_AWID; //przypisanie ID transakcji
      index_cnt <= i_AWADDR;
      size <= (1<<i_AWSIZE); //zdekodowanie AxSIZE - 2^AxSIZE, 1 w prawo przesuniecie to 2
      length <= i_AWLEN;
    end

    if(next_state == bridge_ADDR_READ && i_ARBURST == 2'b01) begin
      index_cnt <= i_ARADDR;
      size <= (1<<i_ARSIZE);
      length <= i_ARLEN;
    end
  end
end : p_fsm_sync

always_comb begin : p_fsm_comb
  {o_WREADY, o_RVALID, o_RLAST, o_AWREADY, o_ARREADY} = '0;
  {o_WRITE_ram, o_READ_ram, o_DATA_LOADED, o_BID, o_RID, o_BVALID} = '0;
  {cnt_clr, cnt_en, o_SAMPLE_INDEX_ram} = '0;
  {o_RDATA, o_SAMPLE_ram} = 'x;

  case(state)
    bridge_IDLE : begin
      next_state = bridge_IDLE;
      o_AWREADY = 1'b1;
      o_ARREADY = 1'b1;//
      if(i_AWVALID) begin
        next_state = bridge_ADDR_WRITE;
      end
      if(i_CALC_END && i_ARVALID) begin//
       next_state = bridge_ADDR_READ;//
     end
    end

    bridge_ADDR_WRITE : begin
      o_AWREADY = 1'b1;
      next_state = bridge_DATA_WRITE;
    end

    bridge_DATA_WRITE : begin //Zapis probek do RAMU
    next_state = bridge_DATA_WRITE;
      o_WREADY = 1'b1;
      o_WRITE_ram = 1'b1;
      o_SAMPLE_INDEX_ram = (index_cnt / size);
      o_SAMPLE_ram = i_WDATA;
      if((data_in_burst_cnt/size) == length) begin//
        o_DATA_LOADED = 1'b1; 
        next_state = bridge_WRITE_RESPONSE;
        cnt_clr = 1'b1;
      end
      else if(i_WVALID) begin
        cnt_en = 1'b1;
      end
    end

    bridge_WRITE_RESPONSE : begin
      next_state = bridge_WRITE_RESPONSE;
      o_BVALID = 1'b1;
      o_BID = trans_id;
      if(i_BREADY) begin
        //next_state = bridge_WAIT;
        next_state = bridge_IDLE;
      end
    end

//    bridge_WAIT : begin
//      next_state = bridge_WAIT;
//      o_ARREADY = 1'b1;
//      if(i_CALC_END && i_ARVALID) begin
//        next_state = bridge_ADDR_READ;
//      end
//    end

    bridge_ADDR_READ : begin
      o_ARREADY = 1'b1;
      next_state = bridge_DATA_READ;
    end

    bridge_DATA_READ : begin
      next_state = bridge_DATA_READ;
      o_RVALID = 1'b1;
      o_READ_ram = 1'b1;
      o_SAMPLE_INDEX_ram = (index_cnt / size);
      o_RDATA = i_DATA_FROM_RAM;
      o_RID = trans_id;
      if ((data_in_burst_cnt/size) == length) begin
        next_state = bridge_READ_LAST;
        cnt_clr = 1'b1;//
      end
      else if (i_RREADY) begin
        cnt_en = 1'b1;
      end
    end

    bridge_READ_LAST : begin
      o_RLAST = 1'b1;
      o_RVALID = 1'b1;
      o_READ_ram = 1'b1;
      o_SAMPLE_INDEX_ram = (index_cnt / size);
      o_RDATA = i_DATA_FROM_RAM;
      next_state = bridge_IDLE;
    end

    default : next_state = bridge_IDLE;
  endcase
end : p_fsm_comb

assign current_state = state; //current state at the output, zakomentowac

endmodule

top_axi_lite.sv
// jeżeli coś jest tb, to powinno się tak nazywać. nie powinno być w jednym katalogu TB i RTL

module top_axi_lite;
    parameter DATA_WIDTH = 32;
    parameter ID_W_WIDTH = 2; //obczaic szerokosc
    parameter ID_R_WIDTH = 2;

    logic clk;
    logic n_Reset;
    logic [15:0]  WDATA;
    logic [1:0] WSTRB;
    logic WVALID;
    logic WLAST;
    logic WREADY;

    logic RREADY;
    logic [DATA_WIDTH-1:0] RDATA;
    logic [ID_R_WIDTH-1:0] RID;
    logic RVALID;
    logic RLAST;

    logic [11:0] AWADDR;
    logic [7:0] AWLEN;
    logic [2:0] AWSIZE;
    logic [1:0] AWBURST;
    logic [ID_W_WIDTH-1:0] AWID;
    logic AWVALID;
    logic AWREADY;

    logic [11:0] ARADDR;
    logic [7:0] ARLEN;
    logic [2:0] ARSIZE;
    logic [1:0] ARBURST;
    logic [ID_R_WIDTH-1:0] ARID;
    logic ARVALID;
    logic ARREADY;
    logic BREADY;
    logic BVALID;
    logic [ID_W_WIDTH-1:0] BID;

    logic [1:0] RBURST;
    
    
    logic [1:0] WBURST;
    logic [11:0] SAMP_NUMBER;

logic [31:0] DATA_FROM_RAM;
logic [15:0] RAM_in_axi;
logic [11:0] SAMPLE_INDEX_ram;
logic CALC_END;
logic WRITE_TO_CACHE;
logic LOADED_DATA;
logic WRITE_ram;
logic READ_ram;

Axi_Bridge #(.DATA_WIDTH(DATA_WIDTH), .ID_W_WIDTH(ID_W_WIDTH), .ID_R_WIDTH(ID_R_WIDTH))
slave
(
    .i_clk(clk), .i_rstn(n_Reset),
    // WRITE DATA CHANNEL
    .i_WDATA(WDATA),
    .i_WSTRB(WSTRB),
    .i_WVALID(WVALID), 
    .i_WLAST(WLAST),
    .o_WREADY(WREADY),
    // READ DATA CHANNEL
    .i_RREADY(RREADY),
    .o_RDATA(RDATA),
    .o_RID(RID),
    .o_RVALID(RVALID), 
    .o_RLAST(RLAST),
    // ADDRESS WRITE CHANNEL
    .i_AWADDR(AWADDR),
    .i_AWLEN(AWLEN),
    .i_AWSIZE(AWSIZE),
    .i_AWBURST(AWBURST),
    .i_AWID(AWID),
    .i_AWVALID(AWVALID),
    .o_AWREADY(AWREADY),
    // ADDRESS READ CHANNEL
    .i_ARADDR(ARADDR),
    .i_ARLEN(ARLEN),
    .i_ARSIZE(ARSIZE),
    .i_ARBURST(ARBURST),
    .i_ARID(ARID),
    .i_ARVALID(ARVALID),
    .o_ARREADY(ARREADY),
    // RESPONSE CHANNEL
    .i_BREADY(BREADY),
    .o_BVALID(BVALID),
    .o_BID(BID),
    // REST OF SIGNALS
    .i_DATA_FROM_RAM(DATA_FROM_RAM),
    .i_CALC_END(CALC_END),
    .i_SAMPLES_NUMBER(SAMP_NUMBER),
    .o_DATA_LOADED(LOADED_DATA),
    .o_SAMPLE_ram(RAM_in_axi),
    .o_SAMPLE_INDEX_ram(SAMPLE_INDEX_ram),
    .o_WRITE_ram(WRITE_ram), 
    .o_READ_ram(READ_ram)
    //._fsm current_state // - ZAKOMENTOWAC
); 

/*Axi_Bridge slave(.i_clk(clk), .i_rstn(n_Reset), .i_AWDATA(WDATA),
        .i_DATA_FROM_RAM(DATA_FROM_RAM), .i_AWVALID(WVALID), .i_ARREADY(RREADY),
        .i_CALC_END(CALC_END), .i_SAMPLES_NUMBER(SAMP_NUMBER),
        .o_AWREADY(WREADY), .o_ARVALID(RVALID), .o_DATA_LOADED(LOADED_DATA), 
        .o_ARDATA(RDATA), .o_SAMPLE_ram(RAM_in_axi), .o_AWBURST(WBURST), 
        .o_ARBURST(RBURST), .o_SAMPLE_INDEX_ram(SAMPLE_INDEX_ram),
        .o_WRITE_ram(WRITE_ram), .o_READ_ram(READ_ram)
);*/

RAM ram1(
        .axi_data_in(RAM_in_axi), 
         .axi_adr_in(SAMPLE_INDEX_ram), 
         .axi_write(WRITE_ram),
         .axi_read(READ_ram),
         .axi_data_out(DATA_FROM_RAM),
         .SEND_DATA(),
         .SEND_ADDR(),
         .READ_ADDRESS(),
         .READ_DATA(),
         //
         .write_to_cache(WRITE_TO_CACHE),
         //
         .mode(1'b1), // '1' AXI write and read, load to cache, '0' Circiut write
         .clk(clk)
);

initial begin
    $dumpon;
    $dumpvars;
    $dumpfile("top_axi_lite.vcd");
end
endmodule

verif/dump.vcd
$date
	Sat Jan 25 01:00:03 2025
$end
$version
	Icarus Verilog
$end
$timescale
	1ps
$end
$scope module top_axi_lite $end
$var wire 1 ! WRITE_ram $end
$var wire 1 " WREADY $end
$var wire 12 # SAMPLE_INDEX_ram [11:0] $end
$var wire 1 $ RVALID $end
$var wire 1 % RLAST $end
$var wire 2 & RID [1:0] $end
$var wire 1 ' READ_ram $end
$var wire 32 ( RDATA [31:0] $end
$var wire 16 ) RAM_in_axi [15:0] $end
$var wire 1 * LOADED_DATA $end
$var wire 32 + DATA_FROM_RAM [31:0] $end
$var wire 1 , BVALID $end
$var wire 2 - BID [1:0] $end
$var wire 1 . AWREADY $end
$var wire 1 / ARREADY $end
$var parameter 32 0 DATA_WIDTH $end
$var parameter 32 1 ID_R_WIDTH $end
$var parameter 32 2 ID_W_WIDTH $end
$var reg 12 3 ARADDR [11:0] $end
$var reg 2 4 ARBURST [1:0] $end
$var reg 2 5 ARID [1:0] $end
$var reg 8 6 ARLEN [7:0] $end
$var reg 3 7 ARSIZE [2:0] $end
$var reg 1 8 ARVALID $end
$var reg 12 9 AWADDR [11:0] $end
$var reg 2 : AWBURST [1:0] $end
$var reg 2 ; AWID [1:0] $end
$var reg 8 < AWLEN [7:0] $end
$var reg 3 = AWSIZE [2:0] $end
$var reg 1 > AWVALID $end
$var reg 1 ? BREADY $end
$var reg 1 @ CALC_END $end
$var reg 1 A RREADY $end
$var reg 12 B SAMP_NUMBER [11:0] $end
$var reg 16 C WDATA [15:0] $end
$var reg 1 D WLAST $end
$var reg 1 E WRITE_TO_CACHE $end
$var reg 2 F WSTRB [1:0] $end
$var reg 1 G WVALID $end
$var reg 1 H clk $end
$var reg 1 I n_Reset $end
$scope module ram1 $end
$var wire 12 J READ_ADDRESS [11:0] $end
$var wire 12 K SEND_ADDR [11:0] $end
$var wire 32 L SEND_DATA [31:0] $end
$var wire 1 H clk $end
$var wire 1 M mode $end
$var wire 1 E write_to_cache $end
$var wire 1 ! axi_write $end
$var wire 1 ' axi_read $end
$var wire 16 N axi_data_in [15:0] $end
$var wire 12 O axi_adr_in [11:0] $end
$var reg 16 P READ_DATA [15:0] $end
$var reg 32 Q axi_data_out [31:0] $end
$upscope $end
$scope module slave $end
$var wire 12 R i_ARADDR [11:0] $end
$var wire 2 S i_ARBURST [1:0] $end
$var wire 2 T i_ARID [1:0] $end
$var wire 8 U i_ARLEN [7:0] $end
$var wire 3 V i_ARSIZE [2:0] $end
$var wire 1 8 i_ARVALID $end
$var wire 12 W i_AWADDR [11:0] $end
$var wire 2 X i_AWBURST [1:0] $end
$var wire 2 Y i_AWID [1:0] $end
$var wire 8 Z i_AWLEN [7:0] $end
$var wire 3 [ i_AWSIZE [2:0] $end
$var wire 1 > i_AWVALID $end
$var wire 1 ? i_BREADY $end
$var wire 1 @ i_CALC_END $end
$var wire 32 \ i_DATA_FROM_RAM [31:0] $end
$var wire 1 A i_RREADY $end
$var wire 12 ] i_SAMPLES_NUMBER [11:0] $end
$var wire 16 ^ i_WDATA [15:0] $end
$var wire 1 D i_WLAST $end
$var wire 2 _ i_WSTRB [1:0] $end
$var wire 1 G i_WVALID $end
$var wire 1 H i_clk $end
$var wire 1 I i_rstn $end
$var wire 1 ` current_state $end
$var parameter 32 a DATA_WIDTH $end
$var parameter 32 b ID_R_WIDTH $end
$var parameter 32 c ID_W_WIDTH $end
$var reg 12 d data_in_burst_cnt [11:0] $end
$var reg 12 e index_cnt [11:0] $end
$var reg 8 f length [7:0] $end
$var reg 3 g next_state [2:0] $end
$var reg 1 / o_ARREADY $end
$var reg 1 . o_AWREADY $end
$var reg 2 h o_BID [1:0] $end
$var reg 1 , o_BVALID $end
$var reg 1 * o_DATA_LOADED $end
$var reg 32 i o_RDATA [31:0] $end
$var reg 1 ' o_READ_ram $end
$var reg 2 j o_RID [1:0] $end
$var reg 1 % o_RLAST $end
$var reg 1 $ o_RVALID $end
$var reg 12 k o_SAMPLE_INDEX_ram [11:0] $end
$var reg 16 l o_SAMPLE_ram [15:0] $end
$var reg 1 " o_WREADY $end
$var reg 1 ! o_WRITE_ram $end
$var reg 3 m size [2:0] $end
$var reg 3 n state [2:0] $end
$var reg 2 o trans_id [1:0] $end
$var reg 1 p cnt_clr $end
$var reg 1 q cnt_en $end
$scope begin p_fsm_comb $end
$upscope $end
$scope begin p_fsm_sync $end
$upscope $end
$upscope $end
$upscope $end
$enddefinitions $end
$comment Show the parameter values. $end
$dumpall
b10 c
b10 b
b100000 a
b10 2
b10 1
b100000 0
$end
#0
$dumpvars
0q
0p
bx o
b0 n
b0 m
bx l
b0 k
b0 j
bx i
b0 h
b0 g
b0 f
b0 e
b0 d
0`
bx _
bx ^
b10000000 ]
bx \
bx [
bx Z
bx Y
bx X
bx W
bx V
bx U
bx T
bx S
bx R
bx Q
bx P
b0 O
bx N
1M
bz L
bz K
bz J
0I
1H
xG
bx F
0E
xD
bx C
b10000000 B
xA
0@
x?
x>
bx =
bx <
bx ;
bx :
bx 9
x8
bx 7
bx 6
bx 5
bx 4
bx 3
1/
1.
b0 -
0,
bx +
0*
bx )
bx (
0'
b0 &
0%
0$
b0 #
0"
0!
$end
#5000
0H
#10000
1H
#15000
0H
#20000
1H
1I
#25000
0H
#30000
1`
b11111 f
b10 m
b0 o
b1 n
b10 g
1.
0/
1H
1>
b0 9
b0 W
b0 ;
b0 Y
b1 :
b1 X
b1 =
b1 [
b11111 <
b11111 Z
#35000
0H
#40000
1q
b10111100000110 )
b10111100000110 N
b10111100000110 l
0D
1G
b11 F
b11 _
b10111100000110 C
b10111100000110 ^
0>
1!
1"
0.
0`
b10 n
1H
#45000
0H
#50000
b111111101100011 C
b111111101100011 ^
b1 #
b1 O
b1 k
b111111101100011 )
b111111101100011 N
b111111101100011 l
1q
1!
1"
b10 d
b10 e
1H
#55000
0H
#60000
b1100100011011111 C
b1100100011011111 ^
b1100100011011111 )
b1100100011011111 N
b1100100011011111 l
1q
b10 #
b10 O
b10 k
1!
1"
b100 d
b100 e
1H
#65000
0H
#70000
b100010100011001 C
b100010100011001 ^
b100010100011001 )
b100010100011001 N
b100010100011001 l
1q
b11 #
b11 O
b11 k
1!
1"
b110 d
b110 e
1H
#75000
0H
#80000
b11010110011111 C
b11010110011111 ^
b11010110011111 )
b11010110011111 N
b11010110011111 l
1q
b100 #
b100 O
b100 k
1!
1"
b1000 d
b1000 e
1H
#85000
0H
#90000
b110001110010 C
b110001110010 ^
b110001110010 )
b110001110010 N
b110001110010 l
1q
b101 #
b101 O
b101 k
1!
1"
b1010 d
b1010 e
1H
#95000
0H
#100000
b11111000001100 C
b11111000001100 ^
b11111000001100 )
b11111000001100 N
b11111000001100 l
1q
b110 #
b110 O
b110 k
1!
1"
b1100 d
b1100 e
1H
#105000
0H
#110000
b1110001100011111 C
b1110001100011111 ^
b1110001100011111 )
b1110001100011111 N
b1110001100011111 l
1q
b111 #
b111 O
b111 k
1!
1"
b1110 d
b1110 e
1H
#115000
0H
#120000
b1000111001111010 C
b1000111001111010 ^
b1000111001111010 )
b1000111001111010 N
b1000111001111010 l
1q
b1000 #
b1000 O
b1000 k
1!
1"
b10000 d
b10000 e
1H
#125000
0H
#130000
b110100100001000 C
b110100100001000 ^
b110100100001000 )
b110100100001000 N
b110100100001000 l
1q
b1001 #
b1001 O
b1001 k
1!
1"
b10010 d
b10010 e
1H
#135000
0H
#140000
b110100011111110 C
b110100011111110 ^
b110100011111110 )
b110100011111110 N
b110100011111110 l
1q
b1010 #
b1010 O
b1010 k
1!
1"
b10100 d
b10100 e
1H
#145000
0H
#150000
b101011110010 C
b101011110010 ^
b101011110010 )
b101011110010 N
b101011110010 l
1q
b1011 #
b1011 O
b1011 k
1!
1"
b10110 d
b10110 e
1H
#155000
0H
#160000
b1111000000001 C
b1111000000001 ^
b1111000000001 )
b1111000000001 N
b1111000000001 l
1q
b1100 #
b1100 O
b1100 k
1!
1"
b11000 d
b11000 e
1H
#165000
0H
#170000
b1011011100111110 C
b1011011100111110 ^
b1011011100111110 )
b1011011100111110 N
b1011011100111110 l
1q
b1101 #
b1101 O
b1101 k
1!
1"
b11010 d
b11010 e
1H
#175000
0H
#180000
b110110101100111 C
b110110101100111 ^
b110110101100111 )
b110110101100111 N
b110110101100111 l
1q
b1110 #
b1110 O
b1110 k
1!
1"
b11100 d
b11100 e
1H
#185000
0H
#190000
b1111100011100101 C
b1111100011100101 ^
b1111100011100101 )
b1111100011100101 N
b1111100011100101 l
1q
b1111 #
b1111 O
b1111 k
1!
1"
b11110 d
b11110 e
1H
#195000
0H
#200000
b1001100001100 C
b1001100001100 ^
b1001100001100 )
b1001100001100 N
b1001100001100 l
1q
b10000 #
b10000 O
b10000 k
1!
1"
b100000 d
b100000 e
1H
#205000
0H
#210000
b101011000010 C
b101011000010 ^
b101011000010 )
b101011000010 N
b101011000010 l
1q
b10001 #
b10001 O
b10001 k
1!
1"
b100010 d
b100010 e
1H
#215000
0H
#220000
b1001111000001101 C
b1001111000001101 ^
b1001111000001101 )
b1001111000001101 N
b1001111000001101 l
1q
b10010 #
b10010 O
b10010 k
1!
1"
b100100 d
b100100 e
1H
#225000
0H
#230000
b1001001111001 C
b1001001111001 ^
b1001001111001 )
b1001001111001 N
b1001001111001 l
1q
b10011 #
b10011 O
b10011 k
1!
1"
b100110 d
b100110 e
1H
#235000
0H
#240000
b1001000110010111 C
b1001000110010111 ^
b1001000110010111 )
b1001000110010111 N
b1001000110010111 l
1q
b10100 #
b10100 O
b10100 k
1!
1"
b101000 d
b101000 e
1H
#245000
0H
#250000
b1111111000011010 C
b1111111000011010 ^
b1111111000011010 )
b1111111000011010 N
b1111111000011010 l
1q
b10101 #
b10101 O
b10101 k
1!
1"
b101010 d
b101010 e
1H
#255000
0H
#260000
b1111100010001111 C
b1111100010001111 ^
b1111100010001111 )
b1111100010001111 N
b1111100010001111 l
1q
b10110 #
b10110 O
b10110 k
1!
1"
b101100 d
b101100 e
1H
#265000
0H
#270000
b100100101001001 C
b100100101001001 ^
b100100101001001 )
b100100101001001 N
b100100101001001 l
1q
b10111 #
b10111 O
b10111 k
1!
1"
b101110 d
b101110 e
1H
#275000
0H
#280000
b1010111100000 C
b1010111100000 ^
b1010111100000 )
b1010111100000 N
b1010111100000 l
1q
b11000 #
b11000 O
b11000 k
1!
1"
b110000 d
b110000 e
1H
#285000
0H
#290000
b110111111111000 C
b110111111111000 ^
b110111111111000 )
b110111111111000 N
b110111111111000 l
1q
b11001 #
b11001 O
b11001 k
1!
1"
b110010 d
b110010 e
1H
#295000
0H
#300000
b1011101111101111 C
b1011101111101111 ^
b1011101111101111 )
b1011101111101111 N
b1011101111101111 l
1q
b11010 #
b11010 O
b11010 k
1!
1"
b110100 d
b110100 e
1H
#305000
0H
#310000
b1001101000000011 C
b1001101000000011 ^
b1001101000000011 )
b1001101000000011 N
b1001101000000011 l
1q
b11011 #
b11011 O
b11011 k
1!
1"
b110110 d
b110110 e
1H
#315000
0H
#320000
b10000100011111 C
b10000100011111 ^
b10000100011111 )
b10000100011111 N
b10000100011111 l
1q
b11100 #
b11100 O
b11100 k
1!
1"
b111000 d
b111000 e
1H
#325000
0H
#330000
b1000101010001001 C
b1000101010001001 ^
b1000101010001001 )
b1000101010001001 N
b1000101010001001 l
1q
b11101 #
b11101 O
b11101 k
1!
1"
b111010 d
b111010 e
1H
#335000
0H
#340000
b1011001110000001 C
b1011001110000001 ^
b1011001110000001 )
b1011001110000001 N
b1011001110000001 l
1q
b11110 #
b11110 O
b11110 k
1!
1"
b111100 d
b111100 e
1H
#345000
0H
#350000
1D
b10001110100110 C
b10001110100110 ^
1p
b11 g
1*
b10001110100110 )
b10001110100110 N
b10001110100110 l
0q
b11111 #
b11111 O
b11111 k
1!
1"
b111110 d
b111110 e
1H
#355000
0H
#360000
b0 g
1?
0D
0G
1,
bx )
bx N
bx l
0p
b0 #
b0 O
b0 k
0!
0*
0"
1`
b0 d
b0 e
b11 n
1H
#365000
0H
#370000
1/
1.
0,
0`
b0 n
1H
#375000
0H
#380000
1.
1/
0?
1H
#385000
0H
#390000
b1 g
1.
1/
1>
b1000000 9
b1000000 W
1H
#395000
0H
#400000
b10 g
1.
0/
1`
b1000000 e
b1 n
1H
#405000
0H
#410000
1q
1G
b1011101100101110 C
b1011101100101110 ^
0>
b1011101100101110 )
b1011101100101110 N
b1011101100101110 l
b100000 #
b100000 O
b100000 k
1!
1"
0.
0`
b10 n
1H
#415000
0H
#420000
b11001001 C
b11001001 ^
b11001001 )
b11001001 N
b11001001 l
1q
b100001 #
b100001 O
b100001 k
1!
1"
b10 d
b1000010 e
1H
#425000
0H
#430000
b1110010110101000 C
b1110010110101000 ^
b1110010110101000 )
b1110010110101000 N
b1110010110101000 l
1q
b100010 #
b100010 O
b100010 k
1!
1"
b100 d
b1000100 e
1H
#435000
0H
#440000
b1110000110011110 C
b1110000110011110 ^
b1110000110011110 )
b1110000110011110 N
b1110000110011110 l
1q
b100011 #
b100011 O
b100011 k
1!
1"
b110 d
b1000110 e
1H
#445000
0H
#450000
b111000000101100 C
b111000000101100 ^
b111000000101100 )
b111000000101100 N
b111000000101100 l
1q
b100100 #
b100100 O
b100100 k
1!
1"
b1000 d
b1001000 e
1H
#455000
0H
#460000
b1100111110000110 C
b1100111110000110 ^
b1100111110000110 )
b1100111110000110 N
b1100111110000110 l
1q
b100101 #
b100101 O
b100101 k
1!
1"
b1010 d
b1001010 e
1H
#465000
0H
#470000
b1000101000101001 C
b1000101000101001 ^
b1000101000101001 )
b1000101000101001 N
b1000101000101001 l
1q
b100110 #
b100110 O
b100110 k
1!
1"
b1100 d
b1001100 e
1H
#475000
0H
#480000
b11100011010011 C
b11100011010011 ^
b11100011010011 )
b11100011010011 N
b11100011010011 l
1q
b100111 #
b100111 O
b100111 k
1!
1"
b1110 d
b1001110 e
1H
#485000
0H
#490000
b110100001001 C
b110100001001 ^
b110100001001 )
b110100001001 N
b110100001001 l
1q
b101000 #
b101000 O
b101000 k
1!
1"
b10000 d
b1010000 e
1H
#495000
0H
#500000
b11000110101111 C
b11000110101111 ^
b11000110101111 )
b11000110101111 N
b11000110101111 l
1q
b101001 #
b101001 O
b101001 k
1!
1"
b10010 d
b1010010 e
1H
#505000
0H
#510000
b1000001111001100 C
b1000001111001100 ^
b1000001111001100 )
b1000001111001100 N
b1000001111001100 l
1q
b101010 #
b101010 O
b101010 k
1!
1"
b10100 d
b1010100 e
1H
#515000
0H
#520000
b110010101111100 C
b110010101111100 ^
b110010101111100 )
b110010101111100 N
b110010101111100 l
1q
b101011 #
b101011 O
b101011 k
1!
1"
b10110 d
b1010110 e
1H
#525000
0H
#530000
b111011001001010 C
b111011001001010 ^
b111011001001010 )
b111011001001010 N
b111011001001010 l
1q
b101100 #
b101100 O
b101100 k
1!
1"
b11000 d
b1011000 e
1H
#535000
0H
#540000
b1111100000101001 C
b1111100000101001 ^
b1111100000101001 )
b1111100000101001 N
b1111100000101001 l
1q
b101101 #
b101101 O
b101101 k
1!
1"
b11010 d
b1011010 e
1H
#545000
0H
#550000
b100010101001111 C
b100010101001111 ^
b100010101001111 )
b100010101001111 N
b100010101001111 l
1q
b101110 #
b101110 O
b101110 k
1!
1"
b11100 d
b1011100 e
1H
#555000
0H
#560000
b1011010111001011 C
b1011010111001011 ^
b1011010111001011 )
b1011010111001011 N
b1011010111001011 l
1q
b101111 #
b101111 O
b101111 k
1!
1"
b11110 d
b1011110 e
1H
#565000
0H
#570000
b100011011110010 C
b100011011110010 ^
b100011011110010 )
b100011011110010 N
b100011011110010 l
1q
b110000 #
b110000 O
b110000 k
1!
1"
b100000 d
b1100000 e
1H
#575000
0H
#580000
b110100010111110 C
b110100010111110 ^
b110100010111110 )
b110100010111110 N
b110100010111110 l
1q
b110001 #
b110001 O
b110001 k
1!
1"
b100010 d
b1100010 e
1H
#585000
0H
#590000
b10101101111001 C
b10101101111001 ^
b10101101111001 )
b10101101111001 N
b10101101111001 l
1q
b110010 #
b110010 O
b110010 k
1!
1"
b100100 d
b1100100 e
1H
#595000
0H
#600000
b1111001011111011 C
b1111001011111011 ^
b1111001011111011 )
b1111001011111011 N
b1111001011111011 l
1q
b110011 #
b110011 O
b110011 k
1!
1"
b100110 d
b1100110 e
1H
#605000
0H
#610000
b1100110000011011 C
b1100110000011011 ^
b1100110000011011 )
b1100110000011011 N
b1100110000011011 l
1q
b110100 #
b110100 O
b110100 k
1!
1"
b101000 d
b1101000 e
1H
#615000
0H
#620000
b1011111011000011 C
b1011111011000011 ^
b1011111011000011 )
b1011111011000011 N
b1011111011000011 l
1q
b110101 #
b110101 O
b110101 k
1!
1"
b101010 d
b1101010 e
1H
#625000
0H
#630000
b110011000110101 C
b110011000110101 ^
b110011000110101 )
b110011000110101 N
b110011000110101 l
1q
b110110 #
b110110 O
b110110 k
1!
1"
b101100 d
b1101100 e
1H
#635000
0H
#640000
b1011111010100001 C
b1011111010100001 ^
b1011111010100001 )
b1011111010100001 N
b1011111010100001 l
1q
b110111 #
b110111 O
b110111 k
1!
1"
b101110 d
b1101110 e
1H
#645000
0H
#650000
b1110001111100100 C
b1110001111100100 ^
b1110001111100100 )
b1110001111100100 N
b1110001111100100 l
1q
b111000 #
b111000 O
b111000 k
1!
1"
b110000 d
b1110000 e
1H
#655000
0H
#660000
b1010111001111001 C
b1010111001111001 ^
b1010111001111001 )
b1010111001111001 N
b1010111001111001 l
1q
b111001 #
b111001 O
b111001 k
1!
1"
b110010 d
b1110010 e
1H
#665000
0H
#670000
b1101001111100100 C
b1101001111100100 ^
b1101001111100100 )
b1101001111100100 N
b1101001111100100 l
1q
b111010 #
b111010 O
b111010 k
1!
1"
b110100 d
b1110100 e
1H
#675000
0H
#680000
b1110110101101100 C
b1110110101101100 ^
b1110110101101100 )
b1110110101101100 N
b1110110101101100 l
1q
b111011 #
b111011 O
b111011 k
1!
1"
b110110 d
b1110110 e
1H
#685000
0H
#690000
b1011110010101110 C
b1011110010101110 ^
b1011110010101110 )
b1011110010101110 N
b1011110010101110 l
1q
b111100 #
b111100 O
b111100 k
1!
1"
b111000 d
b1111000 e
1H
#695000
0H
#700000
b1010100110011011 C
b1010100110011011 ^
b1010100110011011 )
b1010100110011011 N
b1010100110011011 l
1q
b111101 #
b111101 O
b111101 k
1!
1"
b111010 d
b1111010 e
1H
#705000
0H
