RAM.sv
`timescale 1ns / 1ps

module RAM(
    input logic [15:0] axi_data_in,
    input logic [11:0] axi_adr_in,
    input logic axi_write,
    input logic axi_read,
    output logic [31:0] axi_data_out,
    
    input logic [31:0] SEND_DATA,
    input logic [11:0] SEND_ADDR,

    input logic [11:0] READ_ADDRESS,
    
    output logic [15:0] READ_DATA,
    //
    input write_to_cache,
    //
    
    input logic mode,
    input logic clk
    );
 
 reg [31:0] MEM [0:4095];
 
/*always @(posedge clk) begin
    if(mode) begin
        if(axi_write)begin
           MEM[axi_adr_in] <= axi_data_in;
           READ_DATA <= MEM[READ_ADDRESS]; // need changes
        end
        else if(axi_read) axi_data_out <= MEM[axi_adr_in];
    end
    else begin
        MEM[SEND_ADDR] <= SEND_DATA;
    end
 end   */
    
    always @(posedge clk) begin
    if(mode) begin
        if(axi_write)begin
           MEM[axi_adr_in] <= axi_data_in;
        end
        else if(axi_read) axi_data_out <= MEM[axi_adr_in];
    end
    else if(write_to_cache)
        READ_DATA <= MEM[READ_ADDRESS]; 
    else begin
        MEM[SEND_ADDR] <= SEND_DATA;
    end
 end   
endmodule

Axi_Bridge_fsm.sv
package Axi_Bridge_fsm;
  typedef enum logic [2:0] {  
    bridge_IDLE = 3'b000,
    bridge_ADDR_WRITE,
    bridge_DATA_WRITE,
    bridge_WRITE_RESPONSE,
    bridge_WAIT,
    bridge_ADDR_READ,
    bridge_DATA_READ
  } bridge_fsm;
endpackage

Axi_Bridge.sv
//`include "Axi_Bridge_fsm.sv"
import Axi_Bridge_fsm::*;
module Axi_Bridge #(
  parameter DATA_WIDTH = 32,
  parameter ID_W_WIDTH = 2, //obczaic szerokosc
  parameter ID_R_WIDTH = 2
)
(
  input i_clk, i_rstn,
  // WRITE DATA CHANNEL
  input [15:0] i_WDATA,
  input [1:0] i_WSTRB,
  input i_WVALID, i_WLAST,
  output logic o_WREADY,
  // READ DATA CHANNEL
  input i_RREADY,
  output logic [DATA_WIDTH-1:0] o_RDATA,
  output logic [ID_R_WIDTH-1:0] o_RID,
  output logic o_RVALID, o_RLAST,
  // ADDRESS WRITE CHANNEL
  input [11:0] i_AWADDR,
  input [7:0] i_AWLEN,
  input [2:0] i_AWSIZE,
  input [1:0] i_AWBURST,
  input [ID_W_WIDTH-1:0] i_AWID,
  input i_AWVALID,
  output logic o_AWREADY,
  // ADDRESS READ CHANNEL
  input [11:0] i_ARADDR,
  input [7:0] i_ARLEN,
  input [2:0] i_ARSIZE,
  input [1:0] i_ARBURST,
  input [ID_R_WIDTH-1:0] i_ARID,
  input i_ARVALID,
  output logic o_ARREADY,
  //WRITE RESPONSE CHANNEL
  input i_BREADY,
  output logic o_BVALID,
  output logic [ID_W_WIDTH-1:0] o_BID,
  // REST OF SIGNALS
  input [DATA_WIDTH-1:0] i_DATA_FROM_RAM,
  input i_CALC_END,
  input [11:0] i_SAMPLES_NUMBER,
  output logic o_DATA_LOADED,
  output logic [15:0] o_SAMPLE_ram,
  output logic [11:0] o_SAMPLE_INDEX_ram,
  output logic o_WRITE_ram, o_READ_ram
  //output bridge_fsm current_state // - ZAKOMENTOWAC
);

bridge_fsm state, next_state;
logic [11:0] index_cnt;
bit cnt_en, cnt_clr;
logic [2:0] size;
logic [7:0] length;
logic [ID_W_WIDTH-1:0] trans_id;

// FSM
always_ff @(posedge i_clk or negedge i_rstn) begin : p_fsm_sync
  if (~i_rstn) begin
    state <= bridge_IDLE;
    {index_cnt, size, length} <= '0;
    trans_id <= 'x;
  end
  else begin
    state <= next_state;
    if(cnt_clr) begin
      index_cnt <= 12'h0;
    end
    else if(cnt_en) begin
      index_cnt <= index_cnt + size; //size from AxSIZE
    end                              // INCR burst addressing

    if(next_state == bridge_ADDR_WRITE && i_AWBURST == 2'b01) begin
      trans_id <= i_AWID; //przypisanie ID transakcji
      index_cnt <= i_AWADDR;
      size <= (1<<i_AWSIZE); //zdekodowanie AxSIZE - 2^AxSIZE, 1 w prawo przesuniecie to 2
      length <= i_AWLEN;
    end

    if(next_state == bridge_ADDR_READ && i_ARBURST == 2'b01) begin
      index_cnt <= i_ARADDR;
      size <= (1<<i_ARSIZE);
      length <= i_ARLEN;
    end
  end
end : p_fsm_sync

always_comb begin : p_fsm_comb
  {o_WREADY, o_RVALID, o_RLAST, o_AWREADY, o_ARREADY} = '0;
  {o_WRITE_ram, o_READ_ram, o_DATA_LOADED, o_BID, o_RID, o_BVALID} = '0;
  {cnt_clr, cnt_en} = '0;
  {o_RDATA, o_SAMPLE_ram, o_SAMPLE_INDEX_ram} = 'x;

  case(state)
    bridge_IDLE : begin
      next_state = bridge_IDLE;
      o_AWREADY = 1'b1;
      if(i_AWVALID) begin
        next_state = bridge_ADDR_WRITE;
      end
    end

    bridge_ADDR_WRITE : begin
      next_state = bridge_ADDR_WRITE;
      o_AWREADY = 1'b1;
      if(!i_AWVALID) begin
      next_state = bridge_DATA_WRITE;
      end
    end

    bridge_DATA_WRITE : begin //Zapis probek do RAMU
    next_state = bridge_DATA_WRITE;
      o_WREADY = 1'b1;
      o_WRITE_ram = 1'b1;
      o_SAMPLE_INDEX_ram = (index_cnt / size);
      o_SAMPLE_ram = i_WDATA;
      if(index_cnt == length/size) begin
        o_DATA_LOADED = 1'b1; 
        next_state = bridge_WRITE_RESPONSE;
        cnt_clr = 1'b1;
      end
      else if(i_WVALID) begin
        cnt_en = 1'b1;
      end
    end

    bridge_WRITE_RESPONSE : begin
      next_state = bridge_WRITE_RESPONSE;
      o_BVALID = 1'b1;
      o_BID = trans_id;
      if(i_BREADY) begin
        next_state = bridge_WAIT;
      end
    end

    bridge_WAIT : begin
      next_state = bridge_WAIT;
      o_ARREADY = 1'b1;
      if(i_CALC_END && i_ARVALID) begin
        next_state = bridge_ADDR_READ;
      end
    end

    // tu nizej do zrobienia, Dotestowania TODO
    bridge_ADDR_READ : begin
      next_state = bridge_ADDR_READ;
      o_ARREADY = 1'b1;
      if(!i_ARVALID) begin
      next_state = bridge_DATA_READ;
      end
    end

    bridge_DATA_READ : begin
      next_state = bridge_DATA_READ;
      o_ARREADY = 1'b1;
      o_READ_ram = 1'b1;
      o_SAMPLE_INDEX_ram = index_cnt;
      o_RDATA = i_DATA_FROM_RAM;
      o_RID = trans_id;
      if (index_cnt == length/size) begin
        o_RLAST = 1'b1;
        cnt_clr = 1'b1;
        next_state = bridge_IDLE;
      end
      else if (i_RREADY) begin
        cnt_en = 1'b1;
      end
    end

    default : next_state = bridge_IDLE;
  endcase
end : p_fsm_comb

assign current_state = state; //current state at the output, zakomentowac

endmodule

top_axi_lite.sv
// jeżeli coś jest tb, to powinno się tak nazywać. nie powinno być w jednym katalogu TB i RTL

module top_axi_lite;
    parameter DATA_WIDTH = 32;
    parameter ID_W_WIDTH = 2; //obczaic szerokosc
    parameter ID_R_WIDTH = 2;

    logic clk;
    logic n_Reset;
    logic [15:0]  WDATA;
    logic [1:0] WSTRB;
    logic WVALID;
    logic WLAST;
    logic WREADY;

    logic RREADY;
    logic [DATA_WIDTH-1:0] RDATA;
    logic [ID_R_WIDTH-1:0] RID;
    logic RVALID;
    logic RLAST;

    logic [11:0] AWADDR;
    logic [7:0] AWLEN;
    logic [2:0] AWSIZE;
    logic [1:0] AWBURST;
    logic [ID_W_WIDTH-1:0] AWID;
    logic AWVALID;
    logic AWREADY;

    logic [11:0] ARADDR;
    logic [7:0] ARLEN;
    logic [2:0] ARSIZE;
    logic [1:0] ARBURST;
    logic [ID_R_WIDTH-1:0] ARID;
    logic ARVALID;
    logic ARREADY;
    logic BREADY;
    logic BVALID;
    logic [ID_W_WIDTH-1:0] BID;

    logic [1:0] RBURST;
    
    
    logic [1:0] WBURST;
    logic [11:0] SAMP_NUMBER;

logic [31:0] DATA_FROM_RAM;
logic [15:0] RAM_in_axi;
logic [11:0] SAMPLE_INDEX_ram;
logic CALC_END;
logic WRITE_TO_CACHE;
logic LOADED_DATA;
logic WRITE_ram;
logic READ_ram;

Axi_Bridge #(.DATA_WIDTH(DATA_WIDTH), .ID_W_WIDTH(ID_W_WIDTH), .ID_R_WIDTH(ID_R_WIDTH))
slave
(
    .i_clk(clk), .i_rstn(n_Reset),
    // WRITE DATA CHANNEL
    .i_WDATA(WDATA),
    .i_WSTRB(WSTRB),
    .i_WVALID(WVALID), 
    .i_WLAST(WLAST),
    .o_WREADY(WREADY),
    // READ DATA CHANNEL
    .i_RREADY(RREADY),
    .o_RDATA(RDATA),
    .o_RID(RID),
    .o_RVALID(RVALID), 
    .o_RLAST(RLAST),
    // ADDRESS WRITE CHANNEL
    .i_AWADDR(AWADDR),
    .i_AWLEN(AWLEN),
    .i_AWSIZE(AWSIZE),
    .i_AWBURST(AWBURST),
    .i_AWID(AWID),
    .i_AWVALID(AWVALID),
    .o_AWREADY(AWREADY),
    // ADDRESS READ CHANNEL
    .i_ARADDR(ARADDR),
    .i_ARLEN(ARLEN),
    .i_ARSIZE(ARSIZE),
    .i_ARBURST(ARBURST),
    .i_ARID(ARID),
    .i_ARVALID(ARVALID),
    .o_ARREADY(ARREADY),
    // RESPONSE CHANNEL
    .i_BREADY(BREADY),
    .o_BVALID(BVALID),
    .o_BID(BID),
    // REST OF SIGNALS
    .i_DATA_FROM_RAM(DATA_FROM_RAM),
    .i_CALC_END(CALC_END),
    .i_SAMPLES_NUMBER(SAMP_NUMBER),
    .o_DATA_LOADED(LOADED_DATA),
    .o_SAMPLE_ram(RAM_in_axi),
    .o_SAMPLE_INDEX_ram(SAMPLE_INDEX_ram),
    .o_WRITE_ram(WRITE_ram), 
    .o_READ_ram(READ_ram)
    //._fsm current_state // - ZAKOMENTOWAC
); 

/*Axi_Bridge slave(.i_clk(clk), .i_rstn(n_Reset), .i_AWDATA(WDATA),
        .i_DATA_FROM_RAM(DATA_FROM_RAM), .i_AWVALID(WVALID), .i_ARREADY(RREADY),
        .i_CALC_END(CALC_END), .i_SAMPLES_NUMBER(SAMP_NUMBER),
        .o_AWREADY(WREADY), .o_ARVALID(RVALID), .o_DATA_LOADED(LOADED_DATA), 
        .o_ARDATA(RDATA), .o_SAMPLE_ram(RAM_in_axi), .o_AWBURST(WBURST), 
        .o_ARBURST(RBURST), .o_SAMPLE_INDEX_ram(SAMPLE_INDEX_ram),
        .o_WRITE_ram(WRITE_ram), .o_READ_ram(READ_ram)
);*/

RAM ram1(
        .axi_data_in(RAM_in_axi), 
         .axi_adr_in(SAMPLE_INDEX_ram), 
         .axi_write(WRITE_ram),
         .axi_read(READ_ram),
         .axi_data_out(DATA_FROM_RAM),
         .SEND_DATA(),
         .SEND_ADDR(),
         .READ_ADDRESS(),
         .READ_DATA(),
         //
         .write_to_cache(WRITE_TO_CACHE),
         //
         .mode(1'b1), // '1' AXI write and read, load to cache, '0' Circiut write
         .clk(clk)
);

initial begin
    $dumpon;
    $dumpvars;
    $dumpfile("top_axi_lite.vcd");
end
endmodule

verif/dump.vcd
$date
	Mon Jan 20 21:33:22 2025
$end
$version
	Icarus Verilog
$end
$timescale
	1ps
$end
$scope module top_axi_lite $end
$var wire 1 ! WRITE_ram $end
$var wire 1 " WREADY $end
$var wire 12 # SAMPLE_INDEX_ram [11:0] $end
$var wire 1 $ RVALID $end
$var wire 1 % RLAST $end
$var wire 2 & RID [1:0] $end
$var wire 1 ' READ_ram $end
$var wire 32 ( RDATA [31:0] $end
$var wire 16 ) RAM_in_axi [15:0] $end
$var wire 1 * LOADED_DATA $end
$var wire 32 + DATA_FROM_RAM [31:0] $end
$var wire 1 , BVALID $end
$var wire 2 - BID [1:0] $end
$var wire 1 . AWREADY $end
$var wire 1 / ARREADY $end
$var parameter 32 0 DATA_WIDTH $end
$var parameter 32 1 ID_R_WIDTH $end
$var parameter 32 2 ID_W_WIDTH $end
$var reg 12 3 ARADDR [11:0] $end
$var reg 2 4 ARBURST [1:0] $end
$var reg 2 5 ARID [1:0] $end
$var reg 8 6 ARLEN [7:0] $end
$var reg 3 7 ARSIZE [2:0] $end
$var reg 1 8 ARVALID $end
$var reg 12 9 AWADDR [11:0] $end
$var reg 2 : AWBURST [1:0] $end
$var reg 2 ; AWID [1:0] $end
$var reg 8 < AWLEN [7:0] $end
$var reg 3 = AWSIZE [2:0] $end
$var reg 1 > AWVALID $end
$var reg 1 ? BREADY $end
$var reg 1 @ CALC_END $end
$var reg 1 A RREADY $end
$var reg 12 B SAMP_NUMBER [11:0] $end
$var reg 16 C WDATA [15:0] $end
$var reg 1 D WLAST $end
$var reg 1 E WRITE_TO_CACHE $end
$var reg 2 F WSTRB [1:0] $end
$var reg 1 G WVALID $end
$var reg 1 H clk $end
$var reg 1 I n_Reset $end
$scope module ram1 $end
$var wire 12 J READ_ADDRESS [11:0] $end
$var wire 12 K SEND_ADDR [11:0] $end
$var wire 32 L SEND_DATA [31:0] $end
$var wire 1 H clk $end
$var wire 1 M mode $end
$var wire 1 E write_to_cache $end
$var wire 1 ! axi_write $end
$var wire 1 ' axi_read $end
$var wire 16 N axi_data_in [15:0] $end
$var wire 12 O axi_adr_in [11:0] $end
$var reg 16 P READ_DATA [15:0] $end
$var reg 32 Q axi_data_out [31:0] $end
$upscope $end
$scope module slave $end
$var wire 12 R i_ARADDR [11:0] $end
$var wire 2 S i_ARBURST [1:0] $end
$var wire 2 T i_ARID [1:0] $end
$var wire 8 U i_ARLEN [7:0] $end
$var wire 3 V i_ARSIZE [2:0] $end
$var wire 1 8 i_ARVALID $end
$var wire 12 W i_AWADDR [11:0] $end
$var wire 2 X i_AWBURST [1:0] $end
$var wire 2 Y i_AWID [1:0] $end
$var wire 8 Z i_AWLEN [7:0] $end
$var wire 3 [ i_AWSIZE [2:0] $end
$var wire 1 > i_AWVALID $end
$var wire 1 ? i_BREADY $end
$var wire 1 @ i_CALC_END $end
$var wire 32 \ i_DATA_FROM_RAM [31:0] $end
$var wire 1 A i_RREADY $end
$var wire 12 ] i_SAMPLES_NUMBER [11:0] $end
$var wire 16 ^ i_WDATA [15:0] $end
$var wire 1 D i_WLAST $end
$var wire 2 _ i_WSTRB [1:0] $end
$var wire 1 G i_WVALID $end
$var wire 1 H i_clk $end
$var wire 1 I i_rstn $end
$var wire 1 ` current_state $end
$var parameter 32 a DATA_WIDTH $end
$var parameter 32 b ID_R_WIDTH $end
$var parameter 32 c ID_W_WIDTH $end
$var reg 12 d index_cnt [11:0] $end
$var reg 8 e length [7:0] $end
$var reg 3 f next_state [2:0] $end
$var reg 1 / o_ARREADY $end
$var reg 1 . o_AWREADY $end
$var reg 2 g o_BID [1:0] $end
$var reg 1 , o_BVALID $end
$var reg 1 * o_DATA_LOADED $end
$var reg 32 h o_RDATA [31:0] $end
$var reg 1 ' o_READ_ram $end
$var reg 2 i o_RID [1:0] $end
$var reg 1 % o_RLAST $end
$var reg 1 $ o_RVALID $end
$var reg 12 j o_SAMPLE_INDEX_ram [11:0] $end
$var reg 16 k o_SAMPLE_ram [15:0] $end
$var reg 1 " o_WREADY $end
$var reg 1 ! o_WRITE_ram $end
$var reg 3 l size [2:0] $end
$var reg 3 m state [2:0] $end
$var reg 2 n trans_id [1:0] $end
$var reg 1 o cnt_clr $end
$var reg 1 p cnt_en $end
$scope begin p_fsm_comb $end
$upscope $end
$scope begin p_fsm_sync $end
$upscope $end
$upscope $end
$upscope $end
$enddefinitions $end
$comment Show the parameter values. $end
$dumpall
b10 c
b10 b
b100000 a
b10 2
b10 1
b100000 0
$end
#0
$dumpvars
0p
0o
bx n
b0 m
b0 l
bx k
bx j
b0 i
bx h
b0 g
b0 f
b0 e
b0 d
0`
bx _
bx ^
b100 ]
bx \
bx [
bx Z
bx Y
bx X
bx W
bx V
bx U
bx T
bx S
bx R
bx Q
bx P
bx O
bx N
1M
bz L
bz K
bz J
0I
1H
xG
bx F
0E
xD
bx C
b100 B
xA
0@
x?
x>
bx =
bx <
bx ;
bx :
bx 9
x8
bx 7
bx 6
bx 5
bx 4
bx 3
0/
1.
b0 -
0,
bx +
0*
bx )
bx (
0'
b0 &
0%
0$
bx #
0"
0!
$end
#5000
0H
#10000
1H
#15000
0H
#20000
1H
1I
#25000
0H
#30000
1`
b1000 e
b10 l
b0 n
b1 m
b1 f
1.
1H
1>
b0 9
b0 W
b0 ;
b0 Y
b1 :
b1 X
b1 =
b1 [
b1000 <
b1000 Z
#35000
0H
#40000
b10 f
1.
0D
1G
b11 F
b11 _
b1011111011101111 C
b1011111011101111 ^
0>
1H
#45000
0H
#50000
b1011101010111110 C
b1011101010111110 ^
1p
b1011101010111110 )
b1011101010111110 N
b1011101010111110 k
b0 #
b0 O
b0 j
1!
1"
0.
0`
b10 m
1H
#55000
0H
#60000
b1011101010111010 C
b1011101010111010 ^
b1011101010111010 )
b1011101010111010 N
b1011101010111010 k
b1 #
b1 O
b1 j
1p
1!
1"
b10 d
1H
#65000
0H
#70000
b1010100111000110 C
b1010100111000110 ^
1o
b11 f
1*
b1010100111000110 )
b1010100111000110 N
b1010100111000110 k
b10 #
b10 O
b10 j
0p
1!
1"
b100 d
1H
#75000
0H
#80000
1,
bx )
bx N
bx k
bx #
bx O
bx j
0o
0!
0*
0"
1`
b0 d
b11 m
1H
